{"code": "sz.002792", "name": "通宇通讯", "industry": "计算机、通信和其他电子设备制造业", "history": [{"date": "2026-06-08", "rank": 1357, "total": 34.4, "washout_quality": 36.0, "probe_test": 15.0, "ma_convergence": 29.8, "launch_readiness": 75.8, "fund_flow": 22.7, "volume_health": 42.0}, {"date": "2026-06-09", "rank": 1609, "total": 32.2, "washout_quality": 30.0, "probe_test": 15.0, "ma_convergence": 39.2, "launch_readiness": 61.8, "fund_flow": 22.1, "volume_health": 37.3}, {"date": "2026-06-10", "rank": 1677, "total": 30.5, "washout_quality": 29.3, "probe_test": 15.0, "ma_convergence": 32.9, "launch_readiness": 61.8, "fund_flow": 18.7, "volume_health": 37.3}, {"date": "2026-06-11", "rank": 1635, "total": 31.6, "washout_quality": 29.6, "probe_test": 15.0, "ma_convergence": 40.8, "launch_readiness": 56.8, "fund_flow": 21.3, "volume_health": 37.3}, {"date": "2026-06-12", "rank": 2078, "total": 21.7, "washout_quality": 29.5, "probe_test": 15.0, "ma_convergence": 29.7, "launch_readiness": 0.0, "fund_flow": 15.9, "volume_health": 37.3}, {"date": "2026-06-15", "rank": 2429, "total": 23.2, "washout_quality": 29.5, "probe_test": 15.0, "ma_convergence": 35.8, "launch_readiness": 0.0, "fund_flow": 21.5, "volume_health": 36.0}, {"date": "2026-06-16", "rank": 2602, "total": 20.8, "washout_quality": 28.5, "probe_test": 15.0, "ma_convergence": 27.3, "launch_readiness": 0.0, "fund_flow": 17.0, "volume_health": 34.7}, {"date": "2026-06-17", "rank": 2466, "total": 23.7, "washout_quality": 28.6, "probe_test": 15.0, "ma_convergence": 31.5, "launch_readiness": 0.0, "fund_flow": 19.6, "volume_health": 49.3}, {"date": "2026-06-18", "rank": 2264, "total": 29.2, "washout_quality": 28.6, "probe_test": 15.0, "ma_convergence": 40.3, "launch_readiness": 11.0, "fund_flow": 26.4, "volume_health": 64.0}, {"date": "2026-06-22", "rank": 2286, "total": 28.3, "washout_quality": 28.4, "probe_test": 15.0, "ma_convergence": 43.5, "launch_readiness": 0.0, "fund_flow": 28.1, "volume_health": 62.7}]}