{"code": "sz.003025", "name": "思进智能", "concept": "工业母机", "history": [{"date": "2026-05-29", "rank": 1200, "total": 47.1, "washout_quality": 56.2, "probe_test": 47.7, "ma_convergence": 53.9, "stock_strength": 45.8, "launch_readiness": 70.6, "volume_price_health": 57.4, "trend_class": "choppy", "trend_class_score": 50.0}, {"date": "2026-06-01", "rank": 1243, "total": 48.0, "washout_quality": 56.2, "probe_test": 47.7, "ma_convergence": 56.5, "stock_strength": 45.8, "launch_readiness": 66.0, "volume_price_health": 54.7, "trend_class": "choppy", "trend_class_score": 50.0}, {"date": "2026-06-02", "rank": 1318, "total": 42.9, "washout_quality": 56.2, "probe_test": 47.7, "ma_convergence": 60.4, "stock_strength": 45.8, "launch_readiness": 4.3, "volume_price_health": 52.5, "trend_class": "choppy", "trend_class_score": 50.0}, {"date": "2026-06-03", "rank": 1334, "total": 41.4, "washout_quality": 58.3, "probe_test": 47.7, "ma_convergence": 57.6, "stock_strength": 45.8, "launch_readiness": 2.7, "volume_price_health": 49.9, "trend_class": "choppy", "trend_class_score": 50.0}, {"date": "2026-06-04", "rank": 1336, "total": 39.4, "washout_quality": 65.2, "probe_test": 47.7, "ma_convergence": 53.0, "stock_strength": 45.8, "launch_readiness": 1.7, "volume_price_health": 46.7, "trend_class": "choppy", "trend_class_score": 50.0}, {"date": "2026-06-05", "rank": 875, "total": 55.3, "washout_quality": 65.2, "probe_test": 47.7, "ma_convergence": 61.5, "stock_strength": 45.8, "launch_readiness": 85.0, "volume_price_health": 56.7, "trend_class": "choppy", "trend_class_score": 50.0}, {"date": "2026-06-08", "rank": 568, "total": 57.6, "washout_quality": 65.2, "probe_test": 61.4, "ma_convergence": 55.3, "stock_strength": 45.8, "launch_readiness": 100.0, "volume_price_health": 47.2, "trend_class": "choppy", "trend_class_score": 50.0}, {"date": "2026-06-09", "rank": 866, "total": 54.6, "washout_quality": 65.2, "probe_test": 61.4, "ma_convergence": 51.5, "stock_strength": 45.8, "launch_readiness": 100.0, "volume_price_health": 47.6, "trend_class": "choppy", "trend_class_score": 50.0}, {"date": "2026-06-10", "rank": 441, "total": 59.8, "washout_quality": 30.0, "probe_test": 44.7, "ma_convergence": 50.2, "stock_strength": 67.4, "launch_readiness": 96.3, "volume_price_health": 48.6, "trend_class": "trend", "trend_class_score": 72.0}, {"date": "2026-06-11", "rank": 536, "total": 58.4, "washout_quality": 30.0, "probe_test": 44.7, "ma_convergence": 41.1, "stock_strength": 67.1, "launch_readiness": 91.0, "volume_price_health": 55.9, "trend_class": "trend", "trend_class_score": 74.0}, {"date": "2026-06-12", "rank": 624, "total": 55.2, "washout_quality": 30.0, "probe_test": 15.0, "ma_convergence": 46.5, "stock_strength": 65.9, "launch_readiness": 87.7, "volume_price_health": 52.0, "trend_class": "trend", "trend_class_score": 78.0}, {"date": "2026-06-15", "rank": 672, "total": 58.3, "washout_quality": 30.0, "probe_test": 15.0, "ma_convergence": 38.6, "stock_strength": 65.9, "launch_readiness": 99.5, "volume_price_health": 63.1, "trend_class": "trend", "trend_class_score": 78.0}, {"date": "2026-06-16", "rank": 627, "total": 58.8, "washout_quality": 30.0, "probe_test": 15.0, "ma_convergence": 32.8, "stock_strength": 66.3, "launch_readiness": 93.1, "volume_price_health": 52.0, "trend_class": "trend", "trend_class_score": 79.0}, {"date": "2026-06-17", "rank": 2341, "total": 0.0, "washout_quality": 0.0, "probe_test": 0.0, "ma_convergence": 0.0, "stock_strength": 0.0, "launch_readiness": 0.0, "volume_price_health": 0.0, "trend_class": "choppy", "trend_class_score": 0.0}, {"date": "2026-06-18", "rank": 2081, "total": 0.0, "washout_quality": 0.0, "probe_test": 0.0, "ma_convergence": 0.0, "stock_strength": 0.0, "launch_readiness": 0.0, "volume_price_health": 0.0, "trend_class": "choppy", "trend_class_score": 0.0}, {"date": "2026-06-22", "rank": 2015, "total": 0.0, "washout_quality": 0.0, "probe_test": 0.0, "ma_convergence": 0.0, "stock_strength": 0.0, "launch_readiness": 0.0, "volume_price_health": 0.0, "trend_class": "choppy", "trend_class_score": 0.0}, {"date": "2026-06-25", "rank": 1665, "total": 0.0, "washout_quality": 0.0, "probe_test": 0.0, "ma_convergence": 0.0, "stock_strength": 0.0, "launch_readiness": 0.0, "volume_price_health": 0.0, "trend_class": "choppy", "trend_class_score": 0.0}, {"date": "2026-06-26", "rank": 2519, "total": 0.0, "washout_quality": 0.0, "probe_test": 0.0, "ma_convergence": 0.0, "stock_strength": 0.0, "launch_readiness": 0.0, "volume_price_health": 0.0, "trend_class": "choppy", "trend_class_score": 0.0}, {"date": "2026-06-29", "rank": 2038, "total": 0.0, "washout_quality": 0.0, "probe_test": 0.0, "ma_convergence": 0.0, "stock_strength": 0.0, "launch_readiness": 0.0, "volume_price_health": 0.0, "trend_class": "choppy", "trend_class_score": 0.0}, {"date": "2026-06-30", "rank": 1947, "total": 0.0, "washout_quality": 0.0, "probe_test": 0.0, "ma_convergence": 0.0, "stock_strength": 0.0, "launch_readiness": 0.0, "volume_price_health": 0.0, "trend_class": "choppy", "trend_class_score": 0.0}, {"date": "2026-07-01", "rank": 2247, "total": 0.0, "washout_quality": 0.0, "probe_test": 0.0, "ma_convergence": 0.0, "stock_strength": 0.0, "launch_readiness": 0.0, "volume_price_health": 0.0, "trend_class": "choppy", "trend_class_score": 0.0}, {"date": "2026-07-02", "rank": 2262, "total": 0.0, "washout_quality": 0.0, "probe_test": 0.0, "ma_convergence": 0.0, "stock_strength": 0.0, "launch_readiness": 0.0, "volume_price_health": 0.0, "trend_class": "choppy", "trend_class_score": 0.0}, {"date": "2026-07-03", "rank": 2277, "total": 0.0, "washout_quality": 0.0, "probe_test": 0.0, "ma_convergence": 0.0, "stock_strength": 0.0, "launch_readiness": 0.0, "volume_price_health": 0.0, "trend_class": "choppy", "trend_class_score": 0.0}], "kline": [{"date": "2026-05-20", "open": 15.36, "high": 15.8, "low": 15.15, "close": 15.63, "volume": 12708234, "pctChg": 0.89, "turn": 5.61}, {"date": "2026-05-21", "open": 15.6, "high": 15.76, "low": 14.72, "close": 14.84, "volume": 12990151, "pctChg": -5.05, "turn": 5.74}, {"date": "2026-05-22", "open": 15.05, "high": 15.12, "low": 14.81, "close": 14.99, "volume": 8127031, "pctChg": 1.0, "turn": 3.59}, {"date": "2026-05-25", "open": 15.0, "high": 15.09, "low": 14.59, "close": 14.73, "volume": 7856501, "pctChg": -1.78, "turn": 3.47}, {"date": "2026-05-26", "open": 14.63, "high": 15.39, "low": 14.48, "close": 15.31, "volume": 13511033, "pctChg": 3.96, "turn": 5.97}, {"date": "2026-05-27", "open": 15.29, "high": 16.28, "low": 15.22, "close": 15.51, "volume": 16271206, "pctChg": 1.29, "turn": 7.19}, {"date": "2026-05-28", "open": 15.51, "high": 15.66, "low": 15.07, "close": 15.31, "volume": 10994553, "pctChg": -1.27, "turn": 4.86}, {"date": "2026-05-29", "open": 15.22, "high": 15.27, "low": 14.21, "close": 14.35, "volume": 12411335, "pctChg": -6.26, "turn": 5.48}, {"date": "2026-06-01", "open": 14.31, "high": 14.9, "low": 14.24, "close": 14.47, "volume": 8286764, "pctChg": 0.83, "turn": 3.66}, {"date": "2026-06-02", "open": 14.42, "high": 15.4, "low": 14.41, "close": 14.56, "volume": 9319107, "pctChg": 0.61, "turn": 4.12}, {"date": "2026-06-03", "open": 14.43, "high": 14.74, "low": 13.95, "close": 14.09, "volume": 10074729, "pctChg": -3.19, "turn": 4.45}, {"date": "2026-06-04", "open": 14.01, "high": 14.4, "low": 13.76, "close": 13.83, "volume": 7810175, "pctChg": -1.89, "turn": 3.45}, {"date": "2026-06-05", "open": 13.75, "high": 14.96, "low": 13.4, "close": 14.68, "volume": 12961054, "pctChg": 6.14, "turn": 5.72}, {"date": "2026-06-08", "open": 14.39, "high": 15.9, "low": 14.22, "close": 15.46, "volume": 18909939, "pctChg": 5.32, "turn": 8.35}, {"date": "2026-06-09", "open": 15.44, "high": 15.88, "low": 15.13, "close": 15.63, "volume": 14583518, "pctChg": 1.15, "turn": 6.44}, {"date": "2026-06-10", "open": 15.54, "high": 17.04, "low": 15.42, "close": 15.93, "volume": 22086232, "pctChg": 1.9, "turn": 9.75}, {"date": "2026-06-11", "open": 15.67, "high": 16.75, "low": 15.67, "close": 16.27, "volume": 16579496, "pctChg": 2.13, "turn": 7.32}, {"date": "2026-06-12", "open": 16.5, "high": 16.73, "low": 16.01, "close": 16.25, "volume": 15745561, "pctChg": -0.12, "turn": 6.95}, {"date": "2026-06-15", "open": 16.26, "high": 16.95, "low": 15.7, "close": 16.93, "volume": 17917468, "pctChg": 4.18, "turn": 7.91}, {"date": "2026-06-16", "open": 16.66, "high": 18.62, "low": 16.63, "close": 17.43, "volume": 35315244, "pctChg": 2.95, "turn": 15.6}, {"date": "2026-06-17", "open": 17.5, "high": 17.59, "low": 16.5, "close": 16.6, "volume": 24536279, "pctChg": -4.76, "turn": 10.84}, {"date": "2026-06-18", "open": 16.6, "high": 17.23, "low": 16.3, "close": 17.0, "volume": 18150091, "pctChg": 2.41, "turn": 8.02}, {"date": "2026-06-22", "open": 17.0, "high": 17.24, "low": 15.98, "close": 16.32, "volume": 15143799, "pctChg": -4.0, "turn": 6.69}, {"date": "2026-06-25", "open": 15.16, "high": 15.4, "low": 14.4, "close": 14.42, "volume": 11755299, "pctChg": -4.5, "turn": 5.19}, {"date": "2026-06-26", "open": 14.31, "high": 14.7, "low": 13.97, "close": 14.0, "volume": 10246050, "pctChg": -2.91, "turn": 4.53}, {"date": "2026-06-29", "open": 13.93, "high": 14.03, "low": 13.17, "close": 13.6, "volume": 12079440, "pctChg": -2.86, "turn": 5.34}, {"date": "2026-06-30", "open": 13.45, "high": 14.52, "low": 13.27, "close": 14.08, "volume": 13663140, "pctChg": 3.53, "turn": 6.03}, {"date": "2026-07-01", "open": 14.08, "high": 14.47, "low": 13.78, "close": 14.36, "volume": 10378282, "pctChg": 1.99, "turn": 4.58}, {"date": "2026-07-02", "open": 14.19, "high": 15.26, "low": 14.1, "close": 14.53, "volume": 11032014, "pctChg": 1.18, "turn": 4.87}, {"date": "2026-07-03", "open": 14.49, "high": 15.57, "low": 14.32, "close": 15.06, "volume": 13946402, "pctChg": 3.65, "turn": 6.16}]}