{"code": "sz.300229", "name": "拓尔思", "industry": "软件和信息技术服务业", "history": [{"date": "2026-06-08", "rank": 1870, "total": 27.4, "washout_quality": 27.9, "probe_test": 53.8, "ma_convergence": 34.1, "stock_strength": NaN, "launch_readiness": 0.0, "fund_flow": 15.2, "volume_health": 8.7}, {"date": "2026-06-09", "rank": 1031, "total": 41.3, "washout_quality": 27.9, "probe_test": 67.8, "ma_convergence": 43.2, "stock_strength": NaN, "launch_readiness": 64.2, "fund_flow": 21.5, "volume_health": 8.7}, {"date": "2026-06-10", "rank": 1386, "total": 34.9, "washout_quality": 28.0, "probe_test": 53.8, "ma_convergence": 39.0, "stock_strength": NaN, "launch_readiness": 48.2, "fund_flow": 16.3, "volume_health": 10.0}, {"date": "2026-06-11", "rank": 1508, "total": 33.7, "washout_quality": 28.5, "probe_test": 53.8, "ma_convergence": 32.7, "stock_strength": NaN, "launch_readiness": 45.2, "fund_flow": 16.3, "volume_health": 11.3}, {"date": "2026-06-12", "rank": 1382, "total": 34.2, "washout_quality": 28.5, "probe_test": 53.8, "ma_convergence": 35.7, "stock_strength": NaN, "launch_readiness": 45.2, "fund_flow": 16.6, "volume_health": 11.3}, {"date": "2026-06-15", "rank": 1637, "total": 36.4, "washout_quality": 28.5, "probe_test": 53.8, "ma_convergence": 48.8, "stock_strength": NaN, "launch_readiness": 40.2, "fund_flow": 20.0, "volume_health": 12.7}, {"date": "2026-06-16", "rank": 2123, "total": 31.5, "washout_quality": 28.6, "probe_test": 53.8, "ma_convergence": 48.1, "stock_strength": NaN, "launch_readiness": 1.0, "fund_flow": 24.3, "volume_health": 11.3}, {"date": "2026-06-17", "rank": 2076, "total": 31.9, "washout_quality": 28.5, "probe_test": 53.8, "ma_convergence": 48.6, "stock_strength": NaN, "launch_readiness": 0.0, "fund_flow": 26.6, "volume_health": 12.7}, {"date": "2026-06-18", "rank": 913, "total": 49.3, "washout_quality": 31.2, "probe_test": 53.8, "ma_convergence": 56.9, "stock_strength": NaN, "launch_readiness": 75.8, "fund_flow": 34.5, "volume_health": 50.7}, {"date": "2026-06-22", "rank": 841, "total": 47.2, "washout_quality": 32.7, "probe_test": 53.8, "ma_convergence": 33.3, "stock_strength": 44.3, "launch_readiness": 80.8, "fund_flow": 57.5, "volume_health": 65.3}], "kline": [{"date": "2026-05-11", "open": 19.63, "high": 20.02, "low": 19.41, "close": 19.65, "volume": 30998374, "pctChg": 0.82, "turn": 3.55}, {"date": "2026-05-12", "open": 19.51, "high": 19.6, "low": 19.04, "close": 19.12, "volume": 24965841, "pctChg": -2.7, "turn": 2.86}, {"date": "2026-05-13", "open": 18.99, "high": 19.41, "low": 18.72, "close": 19.35, "volume": 22033728, "pctChg": 1.2, "turn": 2.52}, {"date": "2026-05-14", "open": 19.6, "high": 19.93, "low": 18.5, "close": 18.57, "volume": 28656725, "pctChg": -4.03, "turn": 3.28}, {"date": "2026-05-15", "open": 18.6, "high": 19.32, "low": 18.57, "close": 18.69, "volume": 29100688, "pctChg": 0.65, "turn": 3.33}, {"date": "2026-05-18", "open": 18.55, "high": 19.27, "low": 18.53, "close": 19.1, "volume": 25578256, "pctChg": 2.19, "turn": 2.93}, {"date": "2026-05-19", "open": 19.01, "high": 19.75, "low": 18.92, "close": 19.58, "volume": 33771675, "pctChg": 2.51, "turn": 3.87}, {"date": "2026-05-20", "open": 19.46, "high": 19.78, "low": 18.85, "close": 18.93, "volume": 28936315, "pctChg": -3.32, "turn": 3.31}, {"date": "2026-05-21", "open": 19.12, "high": 19.4, "low": 18.15, "close": 18.25, "volume": 30088546, "pctChg": -3.59, "turn": 3.45}, {"date": "2026-05-22", "open": 18.33, "high": 18.5, "low": 17.88, "close": 18.37, "volume": 23466038, "pctChg": 0.66, "turn": 2.69}, {"date": "2026-05-25", "open": 18.54, "high": 19.15, "low": 18.24, "close": 18.46, "volume": 22533683, "pctChg": 0.49, "turn": 2.58}, {"date": "2026-05-26", "open": 18.21, "high": 18.21, "low": 17.67, "close": 17.97, "volume": 23196932, "pctChg": -2.65, "turn": 2.66}, {"date": "2026-05-27", "open": 17.96, "high": 18.15, "low": 17.31, "close": 17.33, "volume": 20402118, "pctChg": -3.56, "turn": 2.34}, {"date": "2026-05-28", "open": 17.39, "high": 17.39, "low": 16.5, "close": 17.04, "volume": 27410486, "pctChg": -1.67, "turn": 3.14}, {"date": "2026-05-29", "open": 17.18, "high": 17.5, "low": 16.51, "close": 16.57, "volume": 22983417, "pctChg": -2.76, "turn": 2.63}, {"date": "2026-06-01", "open": 16.65, "high": 17.96, "low": 16.6, "close": 17.37, "volume": 32623504, "pctChg": 4.83, "turn": 3.74}, {"date": "2026-06-02", "open": 17.33, "high": 17.5, "low": 16.63, "close": 16.91, "volume": 21606695, "pctChg": -2.65, "turn": 2.47}, {"date": "2026-06-03", "open": 16.84, "high": 17.02, "low": 16.41, "close": 16.48, "volume": 19830079, "pctChg": -2.54, "turn": 2.27}, {"date": "2026-06-04", "open": 16.35, "high": 16.35, "low": 15.76, "close": 15.96, "volume": 22755266, "pctChg": -3.16, "turn": 2.61}, {"date": "2026-06-05", "open": 15.85, "high": 16.28, "low": 15.61, "close": 15.97, "volume": 17761438, "pctChg": 0.06, "turn": 2.03}, {"date": "2026-06-08", "open": 15.55, "high": 16.03, "low": 15.4, "close": 15.67, "volume": 18485339, "pctChg": -1.88, "turn": 2.12}, {"date": "2026-06-09", "open": 15.9, "high": 16.99, "low": 15.51, "close": 16.8, "volume": 35389703, "pctChg": 7.21, "turn": 4.05}, {"date": "2026-06-10", "open": 16.45, "high": 16.72, "low": 15.8, "close": 15.97, "volume": 22865839, "pctChg": -4.94, "turn": 2.62}, {"date": "2026-06-11", "open": 15.78, "high": 15.95, "low": 14.91, "close": 15.09, "volume": 22442607, "pctChg": -5.51, "turn": 2.57}, {"date": "2026-06-12", "open": 15.4, "high": 15.55, "low": 15.07, "close": 15.15, "volume": 17822107, "pctChg": 0.4, "turn": 2.04}, {"date": "2026-06-15", "open": 15.39, "high": 15.75, "low": 15.32, "close": 15.61, "volume": 18767702, "pctChg": 3.04, "turn": 2.15}, {"date": "2026-06-16", "open": 15.45, "high": 15.67, "low": 15.26, "close": 15.64, "volume": 17570666, "pctChg": 0.19, "turn": 2.01}, {"date": "2026-06-17", "open": 15.51, "high": 15.6, "low": 15.17, "close": 15.3, "volume": 15955736, "pctChg": -2.17, "turn": 1.83}, {"date": "2026-06-18", "open": 15.31, "high": 15.98, "low": 15.04, "close": 15.64, "volume": 24965843, "pctChg": 2.22, "turn": 2.86}, {"date": "2026-06-22", "open": 15.48, "high": 16.25, "low": 15.24, "close": 16.24, "volume": 31962377, "pctChg": 3.84, "turn": 3.66}]}