{"code": "sz.301098", "name": "金埔园林", "concept": "土壤修复", "history": [{"date": "2026-06-09", "rank": 672, "total": 49.6, "washout_quality": 60.0, "probe_test": 49.2, "ma_convergence": 25.4, "stock_strength": 64.7, "launch_readiness": 4.6, "volume_price_health": 40.0, "trend_class": "trend", "trend_class_score": 90.0, "swing_confidence": 1.0}, {"date": "2026-06-10", "rank": 687, "total": 42.4, "washout_quality": 60.2, "probe_test": 65.0, "ma_convergence": 7.3, "stock_strength": 56.1, "launch_readiness": 0.0, "volume_price_health": 24.7, "trend_class": "trend", "trend_class_score": 90.0, "swing_confidence": 1.0}, {"date": "2026-06-11", "rank": 474, "total": 54.6, "washout_quality": 60.2, "probe_test": 65.0, "ma_convergence": 15.2, "stock_strength": 64.7, "launch_readiness": 72.0, "volume_price_health": 30.1, "trend_class": "trend", "trend_class_score": 90.0, "swing_confidence": 1.0}, {"date": "2026-06-12", "rank": 464, "total": 50.3, "washout_quality": 61.5, "probe_test": 65.0, "ma_convergence": 14.0, "stock_strength": 56.1, "launch_readiness": 64.9, "volume_price_health": 29.1, "trend_class": "trend", "trend_class_score": 90.0, "swing_confidence": 1.0}, {"date": "2026-06-15", "rank": 753, "total": 38.6, "washout_quality": 61.7, "probe_test": 65.0, "ma_convergence": 23.4, "stock_strength": 40.8, "launch_readiness": 55.1, "volume_price_health": 33.3, "trend_class": "trend", "trend_class_score": 90.0, "swing_confidence": 1.0}, {"date": "2026-06-16", "rank": 570, "total": 51.9, "washout_quality": 61.7, "probe_test": 65.0, "ma_convergence": 23.2, "stock_strength": 55.6, "launch_readiness": 54.7, "volume_price_health": 41.1, "trend_class": "trend", "trend_class_score": 90.0, "swing_confidence": 1.0}, {"date": "2026-06-17", "rank": 375, "total": 56.8, "washout_quality": 61.7, "probe_test": 65.0, "ma_convergence": 36.4, "stock_strength": 64.7, "launch_readiness": 58.4, "volume_price_health": 40.5, "trend_class": "trend", "trend_class_score": 90.0, "swing_confidence": 1.0}, {"date": "2026-06-18", "rank": 266, "total": 58.9, "washout_quality": 61.7, "probe_test": 65.0, "ma_convergence": 40.0, "stock_strength": 64.7, "launch_readiness": 92.2, "volume_price_health": 33.2, "trend_class": "trend", "trend_class_score": 90.0, "swing_confidence": 1.0}, {"date": "2026-06-22", "rank": 214, "total": 59.0, "washout_quality": 60.6, "probe_test": 65.0, "ma_convergence": 47.0, "stock_strength": 64.7, "launch_readiness": 91.0, "volume_price_health": 34.3, "trend_class": "trend", "trend_class_score": 90.0, "swing_confidence": 1.0}, {"date": "2026-06-25", "rank": 104, "total": 59.4, "washout_quality": 61.4, "probe_test": 65.0, "ma_convergence": 60.6, "stock_strength": 64.7, "launch_readiness": 77.0, "volume_price_health": 38.8, "trend_class": "trend", "trend_class_score": 90.0, "swing_confidence": 1.0}, {"date": "2026-06-26", "rank": 281, "total": 50.6, "washout_quality": 61.9, "probe_test": 65.0, "ma_convergence": 53.8, "stock_strength": 48.3, "launch_readiness": 65.6, "volume_price_health": 44.8, "trend_class": "trend", "trend_class_score": 90.0, "swing_confidence": 1.0}, {"date": "2026-06-29", "rank": 379, "total": 41.8, "washout_quality": 61.9, "probe_test": 65.0, "ma_convergence": 54.1, "stock_strength": 39.0, "launch_readiness": 62.3, "volume_price_health": 56.5, "trend_class": "trend", "trend_class_score": 90.0, "swing_confidence": 1.0}, {"date": "2026-06-30", "rank": 424, "total": 42.8, "washout_quality": 61.9, "probe_test": 65.0, "ma_convergence": 48.0, "stock_strength": 44.3, "launch_readiness": 6.2, "volume_price_health": 53.0, "trend_class": "trend", "trend_class_score": 90.0, "swing_confidence": 1.0}, {"date": "2026-07-01", "rank": 72, "total": 64.0, "washout_quality": 61.9, "probe_test": 65.0, "ma_convergence": 54.7, "stock_strength": 63.1, "launch_readiness": 94.4, "volume_price_health": 57.3, "trend_class": "trend", "trend_class_score": 90.0, "swing_confidence": 1.0}, {"date": "2026-07-02", "rank": 152, "total": 59.5, "washout_quality": 61.5, "probe_test": 65.0, "ma_convergence": 55.8, "stock_strength": 60.5, "launch_readiness": 89.7, "volume_price_health": 42.7, "trend_class": "trend", "trend_class_score": 90.0, "swing_confidence": 1.0}, {"date": "2026-07-03", "rank": 492, "total": 48.1, "washout_quality": 60.6, "probe_test": 65.0, "ma_convergence": 53.2, "stock_strength": 46.6, "launch_readiness": 71.7, "volume_price_health": 37.6, "trend_class": "trend", "trend_class_score": 90.0, "swing_confidence": 1.0}, {"date": "2026-07-06", "rank": 93, "total": 63.1, "washout_quality": 60.6, "probe_test": 65.1, "ma_convergence": 56.1, "stock_strength": 64.7, "launch_readiness": 98.7, "volume_price_health": 48.5, "trend_class": "trend", "trend_class_score": 90.0, "swing_confidence": 1.0}, {"date": "2026-07-07", "rank": 1900, "total": 0.0, "washout_quality": 0.0, "probe_test": 0.0, "ma_convergence": 0.0, "stock_strength": 0.0, "launch_readiness": 0.0, "volume_price_health": 0.0, "trend_class": "choppy", "trend_class_score": 0.0, "swing_confidence": 0.0}, {"date": "2026-07-08", "rank": 1900, "total": 0.0, "washout_quality": 0.0, "probe_test": 0.0, "ma_convergence": 0.0, "stock_strength": 0.0, "launch_readiness": 0.0, "volume_price_health": 0.0, "trend_class": "choppy", "trend_class_score": 0.0, "swing_confidence": 0.0}, {"date": "2026-07-09", "rank": 1889, "total": 0.0, "washout_quality": 0.0, "probe_test": 0.0, "ma_convergence": 0.0, "stock_strength": 0.0, "launch_readiness": 0.0, "volume_price_health": 0.0, "trend_class": "choppy", "trend_class_score": 0.0, "swing_confidence": 0.0}, {"date": "2026-07-10", "rank": 1914, "total": 0.0, "washout_quality": 0.0, "probe_test": 0.0, "ma_convergence": 0.0, "stock_strength": 0.0, "launch_readiness": 0.0, "volume_price_health": 0.0, "trend_class": "choppy", "trend_class_score": 0.0, "swing_confidence": 0.0}, {"date": "2026-07-13", "rank": 2032, "total": 0.0, "washout_quality": 0.0, "probe_test": 0.0, "ma_convergence": 0.0, "stock_strength": 0.0, "launch_readiness": 0.0, "volume_price_health": 0.0, "trend_class": "choppy", "trend_class_score": 0.0, "swing_confidence": 0.0}, {"date": "2026-07-14", "rank": 1905, "total": 0.0, "washout_quality": 0.0, "probe_test": 0.0, "ma_convergence": 0.0, "stock_strength": 0.0, "launch_readiness": 0.0, "volume_price_health": 0.0, "trend_class": "choppy", "trend_class_score": 0.0, "swing_confidence": 0.0}, {"date": "2026-07-15", "rank": 1996, "total": 0.0, "washout_quality": 0.0, "probe_test": 0.0, "ma_convergence": 0.0, "stock_strength": 0.0, "launch_readiness": 0.0, "volume_price_health": 0.0, "trend_class": "choppy", "trend_class_score": 0.0, "swing_confidence": 0.0}], "kline": [{"date": "2026-06-01", "open": 9.94, "high": 10.04, "low": 9.6, "close": 9.68, "volume": 13090384, "pctChg": -2.62, "turn": 8.31}, {"date": "2026-06-02", "open": 9.56, "high": 9.71, "low": 8.82, "close": 9.26, "volume": 19451417, "pctChg": -4.34, "turn": 12.34}, {"date": "2026-06-03", "open": 9.18, "high": 9.44, "low": 8.95, "close": 9.28, "volume": 11192006, "pctChg": 0.22, "turn": 6.71}, {"date": "2026-06-04", "open": 9.09, "high": 9.24, "low": 8.83, "close": 8.97, "volume": 9519686, "pctChg": -3.34, "turn": 5.45}, {"date": "2026-06-05", "open": 8.9, "high": 8.9, "low": 8.43, "close": 8.5, "volume": 13595596, "pctChg": -5.24, "turn": 7.78}, {"date": "2026-06-08", "open": 8.33, "high": 8.55, "low": 7.93, "close": 8.16, "volume": 11151733, "pctChg": -4.0, "turn": 6.38}, {"date": "2026-06-09", "open": 8.26, "high": 9.79, "low": 7.93, "close": 9.38, "volume": 36049404, "pctChg": 14.95, "turn": 20.63}, {"date": "2026-06-10", "open": 9.18, "high": 9.51, "low": 8.25, "close": 8.41, "volume": 29571850, "pctChg": -10.34, "turn": 16.92}, {"date": "2026-06-11", "open": 8.57, "high": 8.93, "low": 8.09, "close": 8.66, "volume": 24912250, "pctChg": 2.97, "turn": 14.25}, {"date": "2026-06-12", "open": 8.74, "high": 9.27, "low": 8.4, "close": 8.41, "volume": 20012244, "pctChg": -2.89, "turn": 11.45}, {"date": "2026-06-15", "open": 8.46, "high": 8.66, "low": 8.09, "close": 8.14, "volume": 15661979, "pctChg": -3.21, "turn": 8.96}, {"date": "2026-06-16", "open": 8.11, "high": 8.7, "low": 7.83, "close": 8.4, "volume": 18323518, "pctChg": 3.19, "turn": 10.48}, {"date": "2026-06-17", "open": 8.21, "high": 8.7, "low": 8.21, "close": 8.6, "volume": 18637064, "pctChg": 2.38, "turn": 10.16}, {"date": "2026-06-18", "open": 8.46, "high": 9.22, "low": 8.46, "close": 8.93, "volume": 20234020, "pctChg": 3.84, "turn": 10.51}, {"date": "2026-06-22", "open": 8.88, "high": 8.93, "low": 8.52, "close": 8.7, "volume": 15475794, "pctChg": -2.58, "turn": 8.04}, {"date": "2026-06-25", "open": 9.03, "high": 9.1, "low": 8.51, "close": 8.65, "volume": 13079550, "pctChg": -4.21, "turn": 6.78}, {"date": "2026-06-26", "open": 8.61, "high": 8.7, "low": 8.14, "close": 8.27, "volume": 11141502, "pctChg": -4.39, "turn": 5.77}, {"date": "2026-06-29", "open": 8.29, "high": 8.35, "low": 7.83, "close": 8.11, "volume": 10476830, "pctChg": -1.93, "turn": 5.43}, {"date": "2026-06-30", "open": 8.04, "high": 8.29, "low": 7.95, "close": 8.2, "volume": 8205865, "pctChg": 1.11, "turn": 4.25}, {"date": "2026-07-01", "open": 8.18, "high": 8.66, "low": 8.15, "close": 8.54, "volume": 11152854, "pctChg": 4.15, "turn": 5.78}, {"date": "2026-07-02", "open": 8.69, "high": 8.94, "low": 8.42, "close": 8.49, "volume": 12298223, "pctChg": -0.59, "turn": 6.37}, {"date": "2026-07-03", "open": 8.65, "high": 8.65, "low": 8.23, "close": 8.24, "volume": 9017535, "pctChg": -2.94, "turn": 4.67}, {"date": "2026-07-06", "open": 8.25, "high": 8.99, "low": 8.25, "close": 8.72, "volume": 15197348, "pctChg": 5.83, "turn": 7.87}, {"date": "2026-07-07", "open": 8.72, "high": 9.06, "low": 8.52, "close": 8.64, "volume": 13181004, "pctChg": -0.92, "turn": 6.83}, {"date": "2026-07-08", "open": 8.68, "high": 8.95, "low": 8.36, "close": 8.38, "volume": 11397514, "pctChg": -3.01, "turn": 5.91}, {"date": "2026-07-09", "open": 8.46, "high": 8.53, "low": 8.06, "close": 8.28, "volume": 10382179, "pctChg": -1.19, "turn": 5.38}, {"date": "2026-07-10", "open": 8.12, "high": 8.94, "low": 8.05, "close": 8.63, "volume": 16339451, "pctChg": 4.23, "turn": 8.47}, {"date": "2026-07-13", "open": 8.63, "high": 8.63, "low": 7.98, "close": 8.03, "volume": 12160841, "pctChg": -6.95, "turn": 6.3}, {"date": "2026-07-14", "open": 7.94, "high": 8.1, "low": 7.3, "close": 7.68, "volume": 16397021, "pctChg": -4.36, "turn": 8.5}, {"date": "2026-07-15", "open": 7.69, "high": 7.87, "low": 7.6, "close": 7.79, "volume": 9174230, "pctChg": 1.43, "turn": 4.75}]}