{"code": "sz.301306", "name": "西测测试", "industry": "专业技术服务业", "history": [{"date": "2026-05-20", "rank": 1543, "total": 11.6, "washout_quality": 69.0, "probe_test": 15.0, "ma_convergence": 21.1, "stock_strength": 34.4, "launch_readiness": 14.3, "volume_price_health": 40.4}, {"date": "2026-05-21", "rank": 1758, "total": 8.3, "washout_quality": 64.9, "probe_test": 15.0, "ma_convergence": 15.3, "stock_strength": 32.8, "launch_readiness": 14.9, "volume_price_health": 40.9}, {"date": "2026-05-22", "rank": 1684, "total": 8.6, "washout_quality": 63.4, "probe_test": 15.0, "ma_convergence": 18.0, "stock_strength": 32.6, "launch_readiness": 18.9, "volume_price_health": 51.6}, {"date": "2026-05-25", "rank": 1720, "total": 6.6, "washout_quality": 61.2, "probe_test": 15.0, "ma_convergence": 19.5, "stock_strength": 30.5, "launch_readiness": 18.6, "volume_price_health": 38.9}, {"date": "2026-05-26", "rank": 1531, "total": 13.4, "washout_quality": 59.0, "probe_test": 15.0, "ma_convergence": 16.3, "stock_strength": 33.3, "launch_readiness": 18.1, "volume_price_health": 44.4}, {"date": "2026-05-27", "rank": 1630, "total": 12.3, "washout_quality": 60.5, "probe_test": 15.0, "ma_convergence": 14.3, "stock_strength": 32.8, "launch_readiness": 17.9, "volume_price_health": 37.1}, {"date": "2026-05-28", "rank": 1750, "total": 11.3, "washout_quality": 61.0, "probe_test": 15.0, "ma_convergence": 19.7, "stock_strength": 31.2, "launch_readiness": 15.8, "volume_price_health": 48.8}, {"date": "2026-05-29", "rank": 1782, "total": 10.7, "washout_quality": 55.1, "probe_test": 15.0, "ma_convergence": 10.6, "stock_strength": 32.2, "launch_readiness": 10.2, "volume_price_health": 35.8}, {"date": "2026-06-01", "rank": 1833, "total": 11.7, "washout_quality": 54.8, "probe_test": 15.0, "ma_convergence": 5.9, "stock_strength": 33.5, "launch_readiness": 8.6, "volume_price_health": 37.1}, {"date": "2026-06-02", "rank": 1805, "total": 13.0, "washout_quality": 59.1, "probe_test": 15.0, "ma_convergence": 8.2, "stock_strength": 33.8, "launch_readiness": 5.7, "volume_price_health": 51.0}, {"date": "2026-06-03", "rank": 1491, "total": 19.9, "washout_quality": 65.4, "probe_test": 62.6, "ma_convergence": 22.5, "stock_strength": 33.1, "launch_readiness": 85.3, "volume_price_health": 40.3}, {"date": "2026-06-04", "rank": 1582, "total": 18.3, "washout_quality": 63.4, "probe_test": 63.5, "ma_convergence": 25.0, "stock_strength": 32.1, "launch_readiness": 80.4, "volume_price_health": 48.3}, {"date": "2026-06-05", "rank": 1576, "total": 20.2, "washout_quality": 66.5, "probe_test": 70.5, "ma_convergence": 41.7, "stock_strength": 32.1, "launch_readiness": 86.1, "volume_price_health": 40.2}, {"date": "2026-06-08", "rank": 67, "total": 44.6, "washout_quality": 65.5, "probe_test": 58.5, "ma_convergence": 36.2, "stock_strength": 48.3, "launch_readiness": 62.5, "volume_price_health": 40.1}, {"date": "2026-06-09", "rank": 323, "total": 38.2, "washout_quality": 66.2, "probe_test": 63.1, "ma_convergence": 54.2, "stock_strength": 41.1, "launch_readiness": 57.6, "volume_price_health": 51.1}, {"date": "2026-06-10", "rank": 2031, "total": 0.1, "washout_quality": 0.0, "probe_test": 62.4, "ma_convergence": 40.5, "stock_strength": 2.0, "launch_readiness": 9.1, "volume_price_health": 42.8}, {"date": "2026-06-11", "rank": 2210, "total": 0.0, "washout_quality": 0.0, "probe_test": 0.0, "ma_convergence": 0.0, "stock_strength": 0.0, "launch_readiness": 0.0, "volume_price_health": 0.0}, {"date": "2026-06-12", "rank": 1802, "total": 0.0, "washout_quality": 0.0, "probe_test": 0.0, "ma_convergence": 0.0, "stock_strength": 0.0, "launch_readiness": 0.0, "volume_price_health": 0.0}, {"date": "2026-06-15", "rank": 2044, "total": 0.0, "washout_quality": 0.0, "probe_test": 0.0, "ma_convergence": 0.0, "stock_strength": 0.0, "launch_readiness": 0.0, "volume_price_health": 0.0}, {"date": "2026-06-16", "rank": 2179, "total": 0.0, "washout_quality": 0.0, "probe_test": 0.0, "ma_convergence": 0.0, "stock_strength": 0.0, "launch_readiness": 0.0, "volume_price_health": 0.0}, {"date": "2026-06-17", "rank": 2199, "total": 0.0, "washout_quality": 0.0, "probe_test": 0.0, "ma_convergence": 0.0, "stock_strength": 0.0, "launch_readiness": 0.0, "volume_price_health": 0.0}, {"date": "2026-06-18", "rank": 2179, "total": 0.0, "washout_quality": 0.0, "probe_test": 0.0, "ma_convergence": 0.0, "stock_strength": 0.0, "launch_readiness": 0.0, "volume_price_health": 0.0}, {"date": "2026-06-22", "rank": 2101, "total": 0.0, "washout_quality": 0.0, "probe_test": 0.0, "ma_convergence": 0.0, "stock_strength": 0.0, "launch_readiness": 0.0, "volume_price_health": 0.0}, {"date": "2026-06-25", "rank": 1463, "total": 0.0, "washout_quality": 0.0, "probe_test": 0.0, "ma_convergence": 0.0, "stock_strength": 0.0, "launch_readiness": 0.0, "volume_price_health": 0.0}, {"date": "2026-06-26", "rank": 2121, "total": 0.0, "washout_quality": 0.0, "probe_test": 0.0, "ma_convergence": 0.0, "stock_strength": 0.0, "launch_readiness": 0.0, "volume_price_health": 0.0}], "kline": [{"date": "2026-05-13", "open": 163.94, "high": 165.94, "low": 159.0, "close": 163.8, "volume": 4747643, "pctChg": -1.69, "turn": 8.15}, {"date": "2026-05-14", "open": 163.18, "high": 163.75, "low": 153.14, "close": 153.14, "volume": 4197741, "pctChg": -6.51, "turn": 7.2}, {"date": "2026-05-15", "open": 153.31, "high": 158.2, "low": 151.13, "close": 155.79, "volume": 3963417, "pctChg": 1.73, "turn": 6.8}, {"date": "2026-05-18", "open": 154.23, "high": 156.83, "low": 149.0, "close": 150.5, "volume": 4152507, "pctChg": -3.4, "turn": 7.13}, {"date": "2026-05-19", "open": 149.01, "high": 151.0, "low": 141.2, "close": 141.58, "volume": 4264902, "pctChg": -5.93, "turn": 7.32}, {"date": "2026-05-20", "open": 141.6, "high": 148.45, "low": 141.6, "close": 144.58, "volume": 3909011, "pctChg": 2.12, "turn": 6.71}, {"date": "2026-05-21", "open": 143.02, "high": 145.45, "low": 136.81, "close": 137.38, "volume": 3140546, "pctChg": -4.98, "turn": 5.39}, {"date": "2026-05-22", "open": 137.46, "high": 141.92, "low": 134.26, "close": 141.18, "volume": 3287368, "pctChg": 2.77, "turn": 5.64}, {"date": "2026-05-25", "open": 141.2, "high": 145.58, "low": 138.6, "close": 141.08, "volume": 3035826, "pctChg": -0.07, "turn": 5.21}, {"date": "2026-05-26", "open": 140.0, "high": 141.0, "low": 132.9, "close": 136.14, "volume": 3262831, "pctChg": -3.5, "turn": 5.6}, {"date": "2026-05-27", "open": 136.81, "high": 138.88, "low": 131.66, "close": 133.97, "volume": 2453148, "pctChg": -1.59, "turn": 4.21}, {"date": "2026-05-28", "open": 133.34, "high": 137.5, "low": 131.41, "close": 136.36, "volume": 2502370, "pctChg": 1.78, "turn": 4.29}, {"date": "2026-05-29", "open": 136.36, "high": 137.69, "low": 128.7, "close": 129.5, "volume": 2645841, "pctChg": -5.03, "turn": 4.54}, {"date": "2026-06-01", "open": 130.0, "high": 131.0, "low": 126.52, "close": 126.61, "volume": 1512980, "pctChg": -2.23, "turn": 2.6}, {"date": "2026-06-02", "open": 127.6, "high": 128.54, "low": 120.15, "close": 126.96, "volume": 2577238, "pctChg": 0.28, "turn": 4.42}, {"date": "2026-06-03", "open": 125.7, "high": 138.88, "low": 125.14, "close": 134.29, "volume": 4669230, "pctChg": 5.77, "turn": 8.01}, {"date": "2026-06-04", "open": 134.03, "high": 135.0, "low": 128.27, "close": 133.5, "volume": 2996534, "pctChg": -0.59, "turn": 5.14}, {"date": "2026-06-05", "open": 134.06, "high": 139.88, "low": 130.34, "close": 134.9, "volume": 5898021, "pctChg": 1.05, "turn": 10.12}, {"date": "2026-06-08", "open": 129.55, "high": 136.83, "low": 123.0, "close": 126.45, "volume": 3913116, "pctChg": -6.26, "turn": 6.72}, {"date": "2026-06-09", "open": 128.0, "high": 129.68, "low": 123.3, "close": 129.08, "volume": 3005949, "pctChg": 2.08, "turn": 5.16}, {"date": "2026-06-10", "open": 128.34, "high": 129.98, "low": 122.19, "close": 124.27, "volume": 2381445, "pctChg": -3.73, "turn": 4.09}, {"date": "2026-06-11", "open": 124.0, "high": 125.24, "low": 121.0, "close": 123.7, "volume": 2003425, "pctChg": -0.46, "turn": 3.44}, {"date": "2026-06-12", "open": 126.98, "high": 141.0, "low": 125.34, "close": 135.13, "volume": 6075044, "pctChg": 9.24, "turn": 10.43}, {"date": "2026-06-15", "open": 133.2, "high": 140.77, "low": 130.15, "close": 139.93, "volume": 5152649, "pctChg": 3.55, "turn": 8.84}, {"date": "2026-06-16", "open": 142.73, "high": 152.0, "low": 137.9, "close": 140.71, "volume": 6454901, "pctChg": 0.56, "turn": 11.08}, {"date": "2026-06-17", "open": 137.0, "high": 168.0, "low": 135.08, "close": 164.9, "volume": 9581662, "pctChg": 17.19, "turn": 16.45}, {"date": "2026-06-18", "open": 164.5, "high": 178.0, "low": 160.1, "close": 174.0, "volume": 7193455, "pctChg": 5.52, "turn": 12.35}, {"date": "2026-06-22", "open": 176.0, "high": 179.66, "low": 163.26, "close": 167.55, "volume": 4718400, "pctChg": -3.71, "turn": 8.1}, {"date": "2026-06-25", "open": 159.0, "high": 168.85, "low": 158.5, "close": 164.13, "volume": 3830609, "pctChg": 2.41, "turn": 6.57}, {"date": "2026-06-26", "open": 162.36, "high": 172.99, "low": 159.95, "close": 168.0, "volume": 5083840, "pctChg": 2.36, "turn": 8.73}]}