{"code": "sz.301309", "name": "万得凯", "industry": "通用设备制造业", "history": [{"date": "2026-06-08", "rank": 1999, "total": 25.4, "washout_quality": 47.4, "probe_test": 15.0, "ma_convergence": 41.9, "launch_readiness": 0.0, "fund_flow": 12.8, "volume_health": 20.0}, {"date": "2026-06-09", "rank": 2155, "total": 23.9, "washout_quality": 43.3, "probe_test": 15.0, "ma_convergence": 40.0, "launch_readiness": 0.0, "fund_flow": 14.5, "volume_health": 16.7}, {"date": "2026-06-10", "rank": 2216, "total": 22.1, "washout_quality": 38.4, "probe_test": 15.0, "ma_convergence": 38.4, "launch_readiness": 0.0, "fund_flow": 15.2, "volume_health": 12.0}, {"date": "2026-06-11", "rank": 2153, "total": 23.8, "washout_quality": 42.8, "probe_test": 15.0, "ma_convergence": 37.8, "launch_readiness": 0.0, "fund_flow": 15.8, "volume_health": 18.0}, {"date": "2026-06-12", "rank": 1359, "total": 34.5, "washout_quality": 42.8, "probe_test": 15.0, "ma_convergence": 43.6, "launch_readiness": 53.0, "fund_flow": 23.7, "volume_health": 34.0}, {"date": "2026-06-15", "rank": 1421, "total": 39.0, "washout_quality": 44.6, "probe_test": 15.0, "ma_convergence": 55.5, "launch_readiness": 53.0, "fund_flow": 27.0, "volume_health": 47.3}, {"date": "2026-06-16", "rank": 1293, "total": 42.6, "washout_quality": 49.3, "probe_test": 15.0, "ma_convergence": 64.8, "launch_readiness": 50.0, "fund_flow": 33.6, "volume_health": 52.0}, {"date": "2026-06-17", "rank": 1028, "total": 46.7, "washout_quality": 50.9, "probe_test": 15.0, "ma_convergence": 76.0, "launch_readiness": 60.0, "fund_flow": 37.0, "volume_health": 53.3}, {"date": "2026-06-18", "rank": 1034, "total": 47.5, "washout_quality": 57.5, "probe_test": 15.0, "ma_convergence": 76.1, "launch_readiness": 50.0, "fund_flow": 37.4, "volume_health": 58.0}, {"date": "2026-06-22", "rank": 1683, "total": 39.1, "washout_quality": 51.7, "probe_test": 15.0, "ma_convergence": 77.4, "launch_readiness": 1.0, "fund_flow": 34.1, "volume_health": 53.3}]}