{"code": "sh.603049", "name": "中策橡胶", "concept": "融资融券", "history": [{"date": "2026-07-06", "rank": 1957, "total": 0.0, "washout_quality": 0.0, "probe_test": 0.0, "ma_convergence": 0.0, "stock_strength": 0.0, "launch_readiness": 0.0, "volume_price_health": 0.0, "trend_class": "choppy", "trend_class_score": 0.0, "swing_confidence": 0.0}], "kline": [{"date": "2026-05-20", "open": 47.4, "high": 47.76, "low": 46.8, "close": 47.19, "volume": 2004531, "pctChg": -0.92, "turn": 2.29}, {"date": "2026-05-21", "open": 47.2, "high": 48.22, "low": 47.2, "close": 47.29, "volume": 2624764, "pctChg": 0.21, "turn": 3.0}, {"date": "2026-05-22", "open": 47.55, "high": 47.83, "low": 46.91, "close": 47.71, "volume": 1529645, "pctChg": 0.89, "turn": 1.75}, {"date": "2026-05-25", "open": 47.51, "high": 48.3, "low": 47.51, "close": 47.96, "volume": 1774396, "pctChg": 0.52, "turn": 2.03}, {"date": "2026-05-26", "open": 47.86, "high": 48.42, "low": 47.32, "close": 48.24, "volume": 2026115, "pctChg": 0.58, "turn": 2.32}, {"date": "2026-05-27", "open": 48.3, "high": 48.3, "low": 47.0, "close": 47.11, "volume": 1959725, "pctChg": -2.34, "turn": 2.24}, {"date": "2026-05-28", "open": 47.01, "high": 47.15, "low": 46.4, "close": 46.58, "volume": 1584315, "pctChg": -1.12, "turn": 1.81}, {"date": "2026-05-29", "open": 46.66, "high": 46.98, "low": 46.43, "close": 46.5, "volume": 1346029, "pctChg": -0.17, "turn": 1.54}, {"date": "2026-06-01", "open": 46.79, "high": 48.28, "low": 46.35, "close": 47.48, "volume": 2593805, "pctChg": 2.11, "turn": 2.97}, {"date": "2026-06-02", "open": 47.41, "high": 47.79, "low": 46.75, "close": 47.53, "volume": 1829513, "pctChg": 0.11, "turn": 2.09}, {"date": "2026-06-03", "open": 47.53, "high": 47.53, "low": 46.65, "close": 46.8, "volume": 1916890, "pctChg": -1.54, "turn": 2.19}, {"date": "2026-06-04", "open": 46.51, "high": 46.8, "low": 45.72, "close": 45.97, "volume": 2060049, "pctChg": -1.77, "turn": 2.36}, {"date": "2026-06-05", "open": 46.27, "high": 47.13, "low": 45.73, "close": 46.6, "volume": 2025358, "pctChg": 1.37, "turn": 0.4}, {"date": "2026-06-08", "open": 46.03, "high": 46.52, "low": 45.4, "close": 45.89, "volume": 1633680, "pctChg": -1.52, "turn": 0.32}, {"date": "2026-06-09", "open": 46.01, "high": 46.1, "low": 45.56, "close": 46.05, "volume": 1264520, "pctChg": 0.35, "turn": 0.25}, {"date": "2026-06-10", "open": 45.9, "high": 46.1, "low": 45.29, "close": 46.05, "volume": 1413338, "pctChg": 0.0, "turn": 0.28}, {"date": "2026-06-11", "open": 45.78, "high": 46.23, "low": 45.19, "close": 45.24, "volume": 1406300, "pctChg": -1.76, "turn": 0.28}, {"date": "2026-06-15", "open": 46.63, "high": 47.91, "low": 46.56, "close": 47.29, "volume": 4023784, "pctChg": 2.18, "turn": 0.8}, {"date": "2026-06-16", "open": 47.13, "high": 47.18, "low": 45.93, "close": 45.95, "volume": 2801674, "pctChg": -2.83, "turn": 0.55}, {"date": "2026-06-17", "open": 45.95, "high": 46.05, "low": 44.9, "close": 45.36, "volume": 2626934, "pctChg": -1.29, "turn": 0.52}, {"date": "2026-06-18", "open": 45.66, "high": 45.66, "low": 44.19, "close": 44.37, "volume": 3024359, "pctChg": -2.18, "turn": 0.6}, {"date": "2026-06-22", "open": 44.31, "high": 45.29, "low": 43.03, "close": 45.27, "volume": 2737831, "pctChg": 2.03, "turn": 0.54}, {"date": "2026-06-24", "open": 44.16, "high": 44.75, "low": 43.92, "close": 44.14, "volume": 1731765, "pctChg": -0.34, "turn": 0.34}, {"date": "2026-06-26", "open": 44.4, "high": 44.57, "low": 43.51, "close": 44.02, "volume": 1648000, "pctChg": -1.26, "turn": 0.33}, {"date": "2026-06-29", "open": 44.01, "high": 45.61, "low": 42.7, "close": 45.4, "volume": 3527256, "pctChg": 3.13, "turn": 0.7}, {"date": "2026-06-30", "open": 45.2, "high": 45.2, "low": 44.04, "close": 44.81, "volume": 2140100, "pctChg": -1.3, "turn": 0.42}, {"date": "2026-07-01", "open": 44.75, "high": 45.42, "low": 44.37, "close": 44.72, "volume": 2269779, "pctChg": -0.2, "turn": 0.45}, {"date": "2026-07-02", "open": 44.75, "high": 45.44, "low": 44.63, "close": 45.2, "volume": 2732087, "pctChg": 1.07, "turn": 0.54}, {"date": "2026-07-03", "open": 45.0, "high": 46.92, "low": 45.0, "close": 46.65, "volume": 3673939, "pctChg": 3.21, "turn": 0.73}, {"date": "2026-07-06", "open": 46.66, "high": 49.38, "low": 46.2, "close": 48.9, "volume": 6880212, "pctChg": 4.82, "turn": 1.36}]}