{"code": "sh.605277", "name": "新亚电子", "industry": "电气机械和器材制造业", "history": [{"date": "2026-06-08", "rank": 2030, "total": 24.9, "washout_quality": 31.7, "probe_test": 15.0, "ma_convergence": 49.0, "launch_readiness": 0.0, "fund_flow": 28.9, "volume_health": 19.3}, {"date": "2026-06-09", "rank": 2130, "total": 24.4, "washout_quality": 31.7, "probe_test": 15.0, "ma_convergence": 58.7, "launch_readiness": 0.0, "fund_flow": 27.4, "volume_health": 3.3}, {"date": "2026-06-10", "rank": 2104, "total": 24.3, "washout_quality": 36.4, "probe_test": 15.0, "ma_convergence": 49.3, "launch_readiness": 0.0, "fund_flow": 24.7, "volume_health": 9.3}, {"date": "2026-06-11", "rank": 1825, "total": 28.8, "washout_quality": 47.7, "probe_test": 15.0, "ma_convergence": 38.9, "launch_readiness": 0.0, "fund_flow": 25.9, "volume_health": 38.7}, {"date": "2026-06-12", "rank": 1847, "total": 26.5, "washout_quality": 49.8, "probe_test": 15.0, "ma_convergence": 31.1, "launch_readiness": 0.0, "fund_flow": 24.0, "volume_health": 28.7}, {"date": "2026-06-15", "rank": 2655, "total": 17.2, "washout_quality": 28.3, "probe_test": 15.0, "ma_convergence": 26.3, "launch_readiness": 0.0, "fund_flow": 18.8, "volume_health": 4.0}, {"date": "2026-06-16", "rank": 2685, "total": 14.5, "washout_quality": 25.4, "probe_test": 15.0, "ma_convergence": 19.1, "launch_readiness": 0.0, "fund_flow": 16.1, "volume_health": 0.0}, {"date": "2026-06-17", "rank": 2642, "total": 14.7, "washout_quality": 25.9, "probe_test": 15.0, "ma_convergence": 13.4, "launch_readiness": 0.0, "fund_flow": 24.2, "volume_health": 0.7}, {"date": "2026-06-18", "rank": 2640, "total": 13.7, "washout_quality": 25.9, "probe_test": 15.0, "ma_convergence": 9.6, "launch_readiness": 0.0, "fund_flow": 22.5, "volume_health": 0.0}, {"date": "2026-06-22", "rank": 2606, "total": 14.5, "washout_quality": 24.6, "probe_test": 15.0, "ma_convergence": 14.2, "launch_readiness": 0.0, "fund_flow": 24.5, "volume_health": 0.0}, {"date": "2026-06-24", "rank": 704, "total": 16.5, "washout_quality": 26.3, "probe_test": 15.0, "ma_convergence": 27.8, "launch_readiness": 0.0, "fund_flow": 19.2, "volume_health": 0.0}]}