{"code": "sh.688031", "name": "星环科技", "industry": "软件和信息技术服务业", "history": [{"date": "2026-06-08", "rank": 117, "total": 61.5, "washout_quality": 52.4, "probe_test": 74.0, "ma_convergence": 72.1, "launch_readiness": 0.0, "fund_flow": 68.3, "volume_health": 100.0}, {"date": "2026-06-09", "rank": 198, "total": 58.9, "washout_quality": 52.4, "probe_test": 74.0, "ma_convergence": 55.3, "launch_readiness": 0.0, "fund_flow": 70.3, "volume_health": 100.0}, {"date": "2026-06-10", "rank": 200, "total": 58.7, "washout_quality": 50.9, "probe_test": 74.0, "ma_convergence": 60.4, "launch_readiness": 0.0, "fund_flow": 64.1, "volume_health": 100.0}, {"date": "2026-06-11", "rank": 232, "total": 56.9, "washout_quality": 47.2, "probe_test": 74.0, "ma_convergence": 60.2, "launch_readiness": 0.0, "fund_flow": 60.4, "volume_health": 96.7}, {"date": "2026-06-12", "rank": 47, "total": 65.8, "washout_quality": 47.2, "probe_test": 74.0, "ma_convergence": 61.6, "launch_readiness": 64.8, "fund_flow": 59.1, "volume_health": 100.0}, {"date": "2026-06-15", "rank": 40, "total": 68.1, "washout_quality": 50.8, "probe_test": 74.0, "ma_convergence": 68.4, "launch_readiness": 64.8, "fund_flow": 61.0, "volume_health": 100.0}, {"date": "2026-06-16", "rank": 92, "total": 66.3, "washout_quality": 50.2, "probe_test": 74.0, "ma_convergence": 64.4, "launch_readiness": 61.8, "fund_flow": 56.4, "volume_health": 100.0}, {"date": "2026-06-17", "rank": 134, "total": 65.7, "washout_quality": 52.7, "probe_test": 74.0, "ma_convergence": 60.1, "launch_readiness": 61.8, "fund_flow": 52.4, "volume_health": 100.0}, {"date": "2026-06-18", "rank": 117, "total": 65.8, "washout_quality": 52.7, "probe_test": 74.0, "ma_convergence": 71.6, "launch_readiness": 67.8, "fund_flow": 34.4, "volume_health": 96.7}, {"date": "2026-06-22", "rank": 1692, "total": 39.0, "washout_quality": 48.4, "probe_test": 15.0, "ma_convergence": 66.7, "launch_readiness": 0.0, "fund_flow": 27.3, "volume_health": 82.0}, {"date": "2026-06-24", "rank": 478, "total": 37.2, "washout_quality": 50.5, "probe_test": 15.0, "ma_convergence": 59.8, "launch_readiness": 0.0, "fund_flow": 26.3, "volume_health": 73.3}]}