{"code": "sh.688159", "name": "有方科技", "industry": "计算机、通信和其他电子设备制造业", "history": [{"date": "2026-05-20", "rank": 367, "total": 28.5, "washout_quality": 64.8, "probe_test": 64.6, "ma_convergence": 27.1, "stock_strength": 50.6, "launch_readiness": 18.7, "volume_price_health": 60.9}, {"date": "2026-05-21", "rank": 638, "total": 25.4, "washout_quality": 58.2, "probe_test": 51.2, "ma_convergence": 23.9, "stock_strength": 51.6, "launch_readiness": 0.0, "volume_price_health": 56.3}, {"date": "2026-05-22", "rank": 618, "total": 25.8, "washout_quality": 58.5, "probe_test": 51.5, "ma_convergence": 30.9, "stock_strength": 47.4, "launch_readiness": 26.6, "volume_price_health": 63.3}, {"date": "2026-05-25", "rank": 661, "total": 25.1, "washout_quality": 58.3, "probe_test": 52.1, "ma_convergence": 33.6, "stock_strength": 46.2, "launch_readiness": 26.9, "volume_price_health": 59.3}, {"date": "2026-05-26", "rank": 920, "total": 22.3, "washout_quality": 56.4, "probe_test": 52.6, "ma_convergence": 32.0, "stock_strength": 44.3, "launch_readiness": 19.4, "volume_price_health": 48.3}, {"date": "2026-05-27", "rank": 971, "total": 22.4, "washout_quality": 50.9, "probe_test": 53.1, "ma_convergence": 29.3, "stock_strength": 45.4, "launch_readiness": 20.8, "volume_price_health": 44.9}, {"date": "2026-05-28", "rank": 1047, "total": 22.5, "washout_quality": 52.3, "probe_test": 53.3, "ma_convergence": 38.6, "stock_strength": 44.3, "launch_readiness": 6.8, "volume_price_health": 57.4}, {"date": "2026-05-29", "rank": 1213, "total": 20.5, "washout_quality": 46.6, "probe_test": 53.1, "ma_convergence": 26.9, "stock_strength": 44.8, "launch_readiness": 2.7, "volume_price_health": 48.1}, {"date": "2026-06-01", "rank": 1501, "total": 18.1, "washout_quality": 46.6, "probe_test": 53.0, "ma_convergence": 8.3, "stock_strength": 44.3, "launch_readiness": 4.0, "volume_price_health": 43.7}, {"date": "2026-06-02", "rank": 1146, "total": 22.7, "washout_quality": 47.7, "probe_test": 15.0, "ma_convergence": 2.3, "stock_strength": 44.5, "launch_readiness": 7.2, "volume_price_health": 42.1}, {"date": "2026-06-03", "rank": 1345, "total": 21.7, "washout_quality": 45.7, "probe_test": 15.0, "ma_convergence": 0.0, "stock_strength": 44.5, "launch_readiness": 8.1, "volume_price_health": 37.1}, {"date": "2026-06-04", "rank": 1314, "total": 22.3, "washout_quality": 49.0, "probe_test": 15.0, "ma_convergence": 0.0, "stock_strength": 44.7, "launch_readiness": 5.4, "volume_price_health": 39.7}, {"date": "2026-06-05", "rank": 1360, "total": 23.5, "washout_quality": 49.0, "probe_test": 15.0, "ma_convergence": 0.0, "stock_strength": 45.3, "launch_readiness": 7.9, "volume_price_health": 45.0}, {"date": "2026-06-08", "rank": 1123, "total": 25.3, "washout_quality": 45.7, "probe_test": 15.0, "ma_convergence": 0.0, "stock_strength": 49.7, "launch_readiness": 3.1, "volume_price_health": 37.7}, {"date": "2026-06-09", "rank": 1179, "total": 26.2, "washout_quality": 48.1, "probe_test": 15.0, "ma_convergence": 0.0, "stock_strength": 47.4, "launch_readiness": 19.0, "volume_price_health": 47.5}, {"date": "2026-06-10", "rank": 1019, "total": 27.6, "washout_quality": 56.3, "probe_test": 15.0, "ma_convergence": 0.0, "stock_strength": 48.9, "launch_readiness": 20.0, "volume_price_health": 36.6}, {"date": "2026-06-11", "rank": 449, "total": 34.2, "washout_quality": 58.7, "probe_test": 15.0, "ma_convergence": 10.2, "stock_strength": 54.1, "launch_readiness": 21.5, "volume_price_health": 46.5}, {"date": "2026-06-12", "rank": 298, "total": 39.2, "washout_quality": 59.2, "probe_test": 15.0, "ma_convergence": 18.2, "stock_strength": 53.3, "launch_readiness": 68.8, "volume_price_health": 41.0}, {"date": "2026-06-15", "rank": 170, "total": 45.8, "washout_quality": 66.9, "probe_test": 15.0, "ma_convergence": 34.5, "stock_strength": 52.4, "launch_readiness": 89.9, "volume_price_health": 53.0}, {"date": "2026-06-16", "rank": 5, "total": 56.5, "washout_quality": 69.9, "probe_test": 64.9, "ma_convergence": 47.1, "stock_strength": 53.2, "launch_readiness": 96.2, "volume_price_health": 49.6}, {"date": "2026-06-17", "rank": 8, "total": 56.9, "washout_quality": 69.4, "probe_test": 69.6, "ma_convergence": 50.6, "stock_strength": 52.2, "launch_readiness": 97.0, "volume_price_health": 48.3}, {"date": "2026-06-18", "rank": 7, "total": 57.7, "washout_quality": 67.3, "probe_test": 66.7, "ma_convergence": 52.4, "stock_strength": 54.5, "launch_readiness": 92.2, "volume_price_health": 46.3}, {"date": "2026-06-22", "rank": 31, "total": 53.4, "washout_quality": 69.6, "probe_test": 70.7, "ma_convergence": 54.9, "stock_strength": 49.2, "launch_readiness": 90.3, "volume_price_health": 39.4}, {"date": "2026-06-24", "rank": 2, "total": 54.4, "washout_quality": 66.7, "probe_test": 66.8, "ma_convergence": 63.6, "stock_strength": 49.5, "launch_readiness": 76.2, "volume_price_health": 54.3}, {"date": "2026-06-26", "rank": 93, "total": 42.9, "washout_quality": 70.6, "probe_test": 60.9, "ma_convergence": 52.4, "stock_strength": 47.2, "launch_readiness": 12.2, "volume_price_health": 42.0}], "kline": [{"date": "2026-05-13", "open": 58.11, "high": 69.09, "low": 58.11, "close": 67.48, "volume": 18583239, "pctChg": 11.17, "turn": 20.04}, {"date": "2026-05-14", "open": 66.81, "high": 70.0, "low": 64.8, "close": 68.31, "volume": 14561381, "pctChg": 1.23, "turn": 15.7}, {"date": "2026-05-15", "open": 69.99, "high": 73.58, "low": 62.33, "close": 63.75, "volume": 18347278, "pctChg": -6.68, "turn": 19.79}, {"date": "2026-05-18", "open": 63.0, "high": 65.5, "low": 61.99, "close": 63.36, "volume": 11043627, "pctChg": -0.61, "turn": 11.91}, {"date": "2026-05-19", "open": 63.4, "high": 65.26, "low": 61.78, "close": 63.15, "volume": 7162591, "pctChg": -0.33, "turn": 7.72}, {"date": "2026-05-20", "open": 62.71, "high": 63.44, "low": 59.0, "close": 60.13, "volume": 10710708, "pctChg": -4.78, "turn": 11.55}, {"date": "2026-05-21", "open": 60.21, "high": 60.75, "low": 53.15, "close": 53.64, "volume": 11989227, "pctChg": -10.79, "turn": 12.93}, {"date": "2026-05-22", "open": 53.94, "high": 56.5, "low": 52.39, "close": 55.57, "volume": 9043266, "pctChg": 3.6, "turn": 9.75}, {"date": "2026-05-25", "open": 55.53, "high": 55.99, "low": 53.88, "close": 55.38, "volume": 6610055, "pctChg": -0.34, "turn": 7.13}, {"date": "2026-05-26", "open": 55.0, "high": 55.06, "low": 51.6, "close": 52.59, "volume": 6420137, "pctChg": -5.04, "turn": 6.92}, {"date": "2026-05-27", "open": 52.61, "high": 52.79, "low": 49.83, "close": 50.4, "volume": 5083786, "pctChg": -4.16, "turn": 5.48}, {"date": "2026-05-28", "open": 50.6, "high": 51.91, "low": 49.45, "close": 51.04, "volume": 5199468, "pctChg": 1.27, "turn": 5.61}, {"date": "2026-05-29", "open": 51.45, "high": 51.61, "low": 46.0, "close": 46.89, "volume": 6128843, "pctChg": -8.13, "turn": 6.61}, {"date": "2026-06-01", "open": 46.89, "high": 49.3, "low": 46.53, "close": 47.4, "volume": 5246436, "pctChg": 1.09, "turn": 5.66}, {"date": "2026-06-02", "open": 47.4, "high": 48.1, "low": 45.02, "close": 46.23, "volume": 4264761, "pctChg": -2.47, "turn": 4.6}, {"date": "2026-06-03", "open": 46.21, "high": 47.56, "low": 45.0, "close": 45.6, "volume": 4284842, "pctChg": -1.36, "turn": 4.62}, {"date": "2026-06-04", "open": 45.12, "high": 45.52, "low": 44.74, "close": 45.08, "volume": 3575454, "pctChg": -1.14, "turn": 3.86}, {"date": "2026-06-05", "open": 45.08, "high": 46.8, "low": 43.7, "close": 45.37, "volume": 4419118, "pctChg": 0.64, "turn": 4.77}, {"date": "2026-06-08", "open": 44.47, "high": 44.51, "low": 41.44, "close": 42.13, "volume": 4628168, "pctChg": -7.14, "turn": 4.99}, {"date": "2026-06-09", "open": 42.99, "high": 43.88, "low": 42.32, "close": 43.75, "volume": 3299875, "pctChg": 3.85, "turn": 3.56}, {"date": "2026-06-10", "open": 43.45, "high": 44.98, "low": 42.7, "close": 43.35, "volume": 3474400, "pctChg": -0.91, "turn": 3.75}, {"date": "2026-06-11", "open": 42.82, "high": 43.09, "low": 41.03, "close": 42.31, "volume": 3211855, "pctChg": -2.4, "turn": 3.46}, {"date": "2026-06-12", "open": 43.16, "high": 44.94, "low": 43.0, "close": 43.29, "volume": 4005303, "pctChg": 2.32, "turn": 4.32}, {"date": "2026-06-15", "open": 44.02, "high": 45.86, "low": 43.9, "close": 45.84, "volume": 4408682, "pctChg": 5.89, "turn": 4.75}, {"date": "2026-06-16", "open": 46.2, "high": 48.98, "low": 45.11, "close": 47.4, "volume": 5876725, "pctChg": 3.4, "turn": 6.34}, {"date": "2026-06-17", "open": 47.0, "high": 48.28, "low": 46.68, "close": 48.0, "volume": 4849664, "pctChg": 1.27, "turn": 5.23}, {"date": "2026-06-18", "open": 47.6, "high": 49.78, "low": 47.5, "close": 49.0, "volume": 4723555, "pctChg": 2.08, "turn": 5.09}, {"date": "2026-06-22", "open": 49.27, "high": 51.55, "low": 47.28, "close": 48.6, "volume": 7421936, "pctChg": -0.82, "turn": 8.0}, {"date": "2026-06-24", "open": 47.2, "high": 47.2, "low": 45.0, "close": 46.8, "volume": 4073104, "pctChg": -0.43, "turn": 4.39}, {"date": "2026-06-26", "open": 44.64, "high": 45.0, "low": 42.26, "close": 42.26, "volume": 5018478, "pctChg": -6.85, "turn": 5.41}]}