{"code": "sh.688345", "name": "博力威", "industry": "电气机械和器材制造业", "history": [{"date": "2026-06-08", "rank": 963, "total": 40.9, "washout_quality": 48.5, "probe_test": 60.0, "ma_convergence": 30.8, "launch_readiness": 0.0, "fund_flow": 24.9, "volume_health": 64.7}, {"date": "2026-06-09", "rank": 1146, "total": 39.5, "washout_quality": 48.5, "probe_test": 60.0, "ma_convergence": 35.6, "launch_readiness": 0.0, "fund_flow": 22.4, "volume_health": 48.7}, {"date": "2026-06-10", "rank": 1146, "total": 39.1, "washout_quality": 48.9, "probe_test": 60.0, "ma_convergence": 33.7, "launch_readiness": 0.0, "fund_flow": 21.7, "volume_health": 47.3}, {"date": "2026-06-11", "rank": 1165, "total": 39.0, "washout_quality": 50.1, "probe_test": 60.0, "ma_convergence": 32.9, "launch_readiness": 0.0, "fund_flow": 18.6, "volume_health": 48.7}, {"date": "2026-06-12", "rank": 415, "total": 51.5, "washout_quality": 50.1, "probe_test": 60.0, "ma_convergence": 36.3, "launch_readiness": 75.8, "fund_flow": 21.2, "volume_health": 63.3}, {"date": "2026-06-15", "rank": 483, "total": 53.8, "washout_quality": 50.1, "probe_test": 60.0, "ma_convergence": 45.1, "launch_readiness": 80.8, "fund_flow": 24.2, "volume_health": 62.0}, {"date": "2026-06-16", "rank": 1036, "total": 46.2, "washout_quality": 50.1, "probe_test": 15.0, "ma_convergence": 62.6, "launch_readiness": 80.8, "fund_flow": 23.3, "volume_health": 60.7}, {"date": "2026-06-17", "rank": 980, "total": 47.3, "washout_quality": 53.4, "probe_test": 15.0, "ma_convergence": 64.5, "launch_readiness": 77.8, "fund_flow": 27.3, "volume_health": 60.7}, {"date": "2026-06-18", "rank": 828, "total": 50.6, "washout_quality": 57.1, "probe_test": 15.0, "ma_convergence": 65.9, "launch_readiness": 87.8, "fund_flow": 34.5, "volume_health": 60.7}, {"date": "2026-06-22", "rank": 758, "total": 51.8, "washout_quality": 53.2, "probe_test": 15.0, "ma_convergence": 66.3, "launch_readiness": 72.8, "fund_flow": 56.2, "volume_health": 72.0}, {"date": "2026-06-24", "rank": 174, "total": 54.1, "washout_quality": 56.9, "probe_test": 15.0, "ma_convergence": 55.5, "launch_readiness": 80.8, "fund_flow": 60.8, "volume_health": 86.7}], "kline": [{"date": "2026-05-12", "open": 53.9, "high": 53.9, "low": 50.6, "close": 52.1, "volume": 3336616, "pctChg": -3.52, "turn": 3.34}, {"date": "2026-05-13", "open": 51.68, "high": 53.28, "low": 51.34, "close": 52.29, "volume": 1958842, "pctChg": 0.36, "turn": 1.96}, {"date": "2026-05-14", "open": 52.47, "high": 57.55, "low": 51.71, "close": 57.22, "volume": 5018408, "pctChg": 9.43, "turn": 5.02}, {"date": "2026-05-15", "open": 57.7, "high": 58.27, "low": 53.2, "close": 54.1, "volume": 4661606, "pctChg": -5.45, "turn": 4.66}, {"date": "2026-05-18", "open": 52.0, "high": 53.57, "low": 51.6, "close": 52.74, "volume": 2776474, "pctChg": -2.51, "turn": 2.78}, {"date": "2026-05-19", "open": 53.73, "high": 62.62, "low": 53.4, "close": 57.92, "volume": 6577668, "pctChg": 9.82, "turn": 6.58}, {"date": "2026-05-20", "open": 59.0, "high": 59.28, "low": 55.1, "close": 57.09, "volume": 4327893, "pctChg": -1.43, "turn": 4.33}, {"date": "2026-05-21", "open": 56.95, "high": 57.3, "low": 53.5, "close": 53.55, "volume": 3372441, "pctChg": -6.2, "turn": 3.37}, {"date": "2026-05-22", "open": 54.0, "high": 56.49, "low": 53.35, "close": 54.63, "volume": 2876496, "pctChg": 2.02, "turn": 2.88}, {"date": "2026-05-25", "open": 55.5, "high": 61.52, "low": 54.87, "close": 59.95, "volume": 5210633, "pctChg": 9.74, "turn": 5.21}, {"date": "2026-05-26", "open": 59.95, "high": 65.48, "low": 58.75, "close": 61.88, "volume": 5761034, "pctChg": 3.22, "turn": 5.76}, {"date": "2026-05-27", "open": 61.61, "high": 62.36, "low": 57.61, "close": 57.76, "volume": 4260739, "pctChg": -6.66, "turn": 4.26}, {"date": "2026-05-28", "open": 57.5, "high": 58.09, "low": 52.41, "close": 55.02, "volume": 4265151, "pctChg": -4.74, "turn": 4.27}, {"date": "2026-05-29", "open": 55.02, "high": 56.0, "low": 51.5, "close": 52.4, "volume": 2834571, "pctChg": -4.76, "turn": 2.83}, {"date": "2026-06-01", "open": 55.0, "high": 55.57, "low": 49.69, "close": 49.78, "volume": 3561226, "pctChg": -5.0, "turn": 3.56}, {"date": "2026-06-02", "open": 49.78, "high": 52.48, "low": 49.5, "close": 51.32, "volume": 2564237, "pctChg": 3.09, "turn": 2.55}, {"date": "2026-06-03", "open": 51.31, "high": 52.31, "low": 49.51, "close": 50.72, "volume": 1893168, "pctChg": -1.17, "turn": 1.88}, {"date": "2026-06-04", "open": 49.88, "high": 50.96, "low": 48.88, "close": 50.6, "volume": 1559988, "pctChg": -0.24, "turn": 1.55}, {"date": "2026-06-05", "open": 50.79, "high": 50.99, "low": 47.08, "close": 49.59, "volume": 2231792, "pctChg": -2.0, "turn": 2.22}, {"date": "2026-06-08", "open": 48.61, "high": 48.61, "low": 46.47, "close": 47.2, "volume": 1690665, "pctChg": -4.82, "turn": 1.68}, {"date": "2026-06-09", "open": 48.38, "high": 48.56, "low": 47.08, "close": 48.03, "volume": 1115432, "pctChg": 1.76, "turn": 1.1}, {"date": "2026-06-10", "open": 48.0, "high": 48.33, "low": 46.0, "close": 47.6, "volume": 1384780, "pctChg": -0.9, "turn": 1.37}, {"date": "2026-06-11", "open": 47.8, "high": 48.28, "low": 46.86, "close": 47.48, "volume": 927570, "pctChg": -0.25, "turn": 0.91}, {"date": "2026-06-12", "open": 48.0, "high": 49.37, "low": 47.34, "close": 48.88, "volume": 2064272, "pctChg": 2.95, "turn": 2.04}, {"date": "2026-06-15", "open": 49.22, "high": 51.18, "low": 48.83, "close": 51.05, "volume": 1929294, "pctChg": 4.44, "turn": 1.9}, {"date": "2026-06-16", "open": 51.57, "high": 52.47, "low": 49.79, "close": 52.0, "volume": 1633380, "pctChg": 1.86, "turn": 1.61}, {"date": "2026-06-17", "open": 51.9, "high": 52.8, "low": 51.1, "close": 52.59, "volume": 1381889, "pctChg": 1.13, "turn": 1.36}, {"date": "2026-06-18", "open": 53.45, "high": 53.45, "low": 51.59, "close": 52.67, "volume": 1537343, "pctChg": 0.15, "turn": 1.52}, {"date": "2026-06-22", "open": 53.06, "high": 55.0, "low": 51.58, "close": 53.67, "volume": 2827473, "pctChg": 1.9, "turn": 2.79}, {"date": "2026-06-24", "open": 55.53, "high": 58.21, "low": 55.53, "close": 56.8, "volume": 2586793, "pctChg": -0.33, "turn": 2.55}]}