{"code": "sh.688429", "name": "时创能源", "concept": "BC电池", "history": [{"date": "2026-05-28", "rank": 1880, "total": 27.4, "washout_quality": 68.4, "probe_test": 15.0, "ma_convergence": 24.7, "stock_strength": 45.2, "launch_readiness": 45.4, "volume_price_health": 32.5, "trend_class": "trend", "trend_class_score": 65.0}, {"date": "2026-05-29", "rank": 1935, "total": 24.0, "washout_quality": 69.5, "probe_test": 15.0, "ma_convergence": 14.9, "stock_strength": 45.2, "launch_readiness": 0.0, "volume_price_health": 28.4, "trend_class": "trend", "trend_class_score": 65.0}, {"date": "2026-06-01", "rank": 2001, "total": 24.6, "washout_quality": 69.5, "probe_test": 15.0, "ma_convergence": 16.8, "stock_strength": 45.2, "launch_readiness": 7.2, "volume_price_health": 29.0, "trend_class": "trend", "trend_class_score": 65.0}, {"date": "2026-06-02", "rank": 2000, "total": 24.0, "washout_quality": 67.1, "probe_test": 15.0, "ma_convergence": 11.8, "stock_strength": 45.2, "launch_readiness": 8.8, "volume_price_health": 27.2, "trend_class": "trend", "trend_class_score": 65.0}, {"date": "2026-06-03", "rank": 2002, "total": 23.5, "washout_quality": 65.5, "probe_test": 15.0, "ma_convergence": 12.2, "stock_strength": 45.2, "launch_readiness": 8.7, "volume_price_health": 25.0, "trend_class": "trend", "trend_class_score": 65.0}, {"date": "2026-06-04", "rank": 2005, "total": 23.2, "washout_quality": 63.1, "probe_test": 15.0, "ma_convergence": 11.1, "stock_strength": 45.2, "launch_readiness": 11.0, "volume_price_health": 24.4, "trend_class": "trend", "trend_class_score": 65.0}, {"date": "2026-06-05", "rank": 2033, "total": 23.3, "washout_quality": 62.2, "probe_test": 15.0, "ma_convergence": 13.3, "stock_strength": 45.2, "launch_readiness": 9.4, "volume_price_health": 27.3, "trend_class": "trend", "trend_class_score": 65.0}, {"date": "2026-06-08", "rank": 2045, "total": 20.4, "washout_quality": 53.4, "probe_test": 15.0, "ma_convergence": 6.6, "stock_strength": 45.2, "launch_readiness": 0.0, "volume_price_health": 19.8, "trend_class": "trend", "trend_class_score": 65.0}, {"date": "2026-06-09", "rank": 2032, "total": 20.6, "washout_quality": 52.5, "probe_test": 15.0, "ma_convergence": 6.9, "stock_strength": 45.2, "launch_readiness": 0.0, "volume_price_health": 22.6, "trend_class": "trend", "trend_class_score": 65.0}, {"date": "2026-06-10", "rank": 2000, "total": 21.5, "washout_quality": 51.7, "probe_test": 15.0, "ma_convergence": 8.1, "stock_strength": 45.2, "launch_readiness": 0.0, "volume_price_health": 31.2, "trend_class": "trend", "trend_class_score": 65.0}, {"date": "2026-06-11", "rank": 1997, "total": 21.9, "washout_quality": 52.0, "probe_test": 15.0, "ma_convergence": 10.3, "stock_strength": 45.2, "launch_readiness": 0.0, "volume_price_health": 33.1, "trend_class": "trend", "trend_class_score": 65.0}, {"date": "2026-06-12", "rank": 1785, "total": 21.8, "washout_quality": 52.0, "probe_test": 15.0, "ma_convergence": 14.4, "stock_strength": 45.2, "launch_readiness": 18.6, "volume_price_health": 22.4, "trend_class": "trend", "trend_class_score": 65.0}, {"date": "2026-06-15", "rank": 2054, "total": 21.2, "washout_quality": 50.7, "probe_test": 15.0, "ma_convergence": 23.2, "stock_strength": 45.2, "launch_readiness": 10.8, "volume_price_health": 20.7, "trend_class": "trend", "trend_class_score": 65.0}, {"date": "2026-06-16", "rank": 2008, "total": 24.1, "washout_quality": 50.7, "probe_test": 15.0, "ma_convergence": 33.6, "stock_strength": 45.2, "launch_readiness": 30.0, "volume_price_health": 32.6, "trend_class": "trend", "trend_class_score": 65.0}, {"date": "2026-06-17", "rank": 1982, "total": 22.1, "washout_quality": 49.4, "probe_test": 15.0, "ma_convergence": 33.2, "stock_strength": 45.2, "launch_readiness": 21.4, "volume_price_health": 22.1, "trend_class": "trend", "trend_class_score": 65.0}, {"date": "2026-06-18", "rank": 1979, "total": 22.0, "washout_quality": 48.6, "probe_test": 15.0, "ma_convergence": 36.1, "stock_strength": 45.2, "launch_readiness": 16.2, "volume_price_health": 23.8, "trend_class": "trend", "trend_class_score": 65.0}, {"date": "2026-06-22", "rank": 1939, "total": 23.3, "washout_quality": 47.5, "probe_test": 15.0, "ma_convergence": 38.3, "stock_strength": 45.2, "launch_readiness": 20.2, "volume_price_health": 34.2, "trend_class": "trend", "trend_class_score": 65.0}, {"date": "2026-06-24", "rank": 538, "total": 21.0, "washout_quality": 44.2, "probe_test": 15.0, "ma_convergence": 35.0, "stock_strength": 45.2, "launch_readiness": 14.1, "volume_price_health": 22.1, "trend_class": "trend", "trend_class_score": 65.0}, {"date": "2026-06-26", "rank": 1839, "total": 19.5, "washout_quality": 43.1, "probe_test": 15.0, "ma_convergence": 32.8, "stock_strength": 45.2, "launch_readiness": 0.0, "volume_price_health": 19.0, "trend_class": "trend", "trend_class_score": 65.0}, {"date": "2026-06-29", "rank": 2571, "total": 0.0, "washout_quality": 0.0, "probe_test": 0.0, "ma_convergence": 0.0, "stock_strength": 0.0, "launch_readiness": 0.0, "volume_price_health": 0.0, "trend_class": "choppy", "trend_class_score": 62.0}, {"date": "2026-06-30", "rank": 2464, "total": 0.0, "washout_quality": 0.0, "probe_test": 0.0, "ma_convergence": 0.0, "stock_strength": 0.0, "launch_readiness": 0.0, "volume_price_health": 0.0, "trend_class": "choppy", "trend_class_score": 62.0}, {"date": "2026-07-01", "rank": 2114, "total": 0.0, "washout_quality": 0.0, "probe_test": 0.0, "ma_convergence": 0.0, "stock_strength": 0.0, "launch_readiness": 0.0, "volume_price_health": 0.0, "trend_class": "choppy", "trend_class_score": 62.0}, {"date": "2026-07-02", "rank": 2338, "total": 0.0, "washout_quality": 0.0, "probe_test": 0.0, "ma_convergence": 0.0, "stock_strength": 0.0, "launch_readiness": 0.0, "volume_price_health": 0.0, "trend_class": "choppy", "trend_class_score": 62.0}], "kline": [{"date": "2026-05-19", "open": 14.11, "high": 14.43, "low": 13.89, "close": 14.13, "volume": 2400614, "pctChg": 0.43, "turn": 2.0}, {"date": "2026-05-20", "open": 14.2, "high": 14.24, "low": 13.71, "close": 14.19, "volume": 3183555, "pctChg": 0.42, "turn": 2.66}, {"date": "2026-05-21", "open": 14.24, "high": 14.32, "low": 13.17, "close": 13.25, "volume": 4274648, "pctChg": -6.62, "turn": 3.57}, {"date": "2026-05-22", "open": 13.3, "high": 13.69, "low": 13.11, "close": 13.63, "volume": 3304947, "pctChg": 2.87, "turn": 2.76}, {"date": "2026-05-25", "open": 13.55, "high": 13.65, "low": 13.13, "close": 13.2, "volume": 2406375, "pctChg": -3.15, "turn": 2.01}, {"date": "2026-05-26", "open": 13.12, "high": 13.24, "low": 12.53, "close": 12.73, "volume": 2966667, "pctChg": -3.56, "turn": 2.48}, {"date": "2026-05-27", "open": 12.77, "high": 13.27, "low": 12.45, "close": 12.59, "volume": 3121356, "pctChg": -1.1, "turn": 2.6}, {"date": "2026-05-28", "open": 12.59, "high": 12.7, "low": 12.2, "close": 12.54, "volume": 3432676, "pctChg": -0.4, "turn": 2.86}, {"date": "2026-05-29", "open": 12.5, "high": 12.7, "low": 11.87, "close": 12.01, "volume": 3242416, "pctChg": -4.23, "turn": 2.71}, {"date": "2026-06-01", "open": 11.91, "high": 12.35, "low": 11.89, "close": 12.2, "volume": 2477366, "pctChg": 1.58, "turn": 2.07}, {"date": "2026-06-02", "open": 12.2, "high": 12.21, "low": 11.71, "close": 11.8, "volume": 2701485, "pctChg": -3.28, "turn": 2.25}, {"date": "2026-06-03", "open": 11.81, "high": 11.96, "low": 11.62, "close": 11.75, "volume": 2456383, "pctChg": -0.42, "turn": 2.05}, {"date": "2026-06-04", "open": 11.7, "high": 11.78, "low": 11.44, "close": 11.61, "volume": 2353434, "pctChg": -1.19, "turn": 1.96}, {"date": "2026-06-05", "open": 11.6, "high": 11.82, "low": 11.21, "close": 11.56, "volume": 2602648, "pctChg": -0.43, "turn": 2.17}, {"date": "2026-06-08", "open": 11.49, "high": 11.58, "low": 10.71, "close": 10.92, "volume": 3360036, "pctChg": -5.54, "turn": 2.8}, {"date": "2026-06-09", "open": 10.97, "high": 11.1, "low": 10.69, "close": 10.91, "volume": 2282506, "pctChg": -0.09, "turn": 1.9}, {"date": "2026-06-10", "open": 10.88, "high": 10.93, "low": 10.37, "close": 10.84, "volume": 3450244, "pctChg": -0.64, "turn": 2.88}, {"date": "2026-06-11", "open": 10.67, "high": 10.84, "low": 10.51, "close": 10.77, "volume": 1900341, "pctChg": -0.65, "turn": 1.59}, {"date": "2026-06-12", "open": 10.86, "high": 11.27, "low": 10.78, "close": 10.9, "volume": 2256708, "pctChg": 1.21, "turn": 1.88}, {"date": "2026-06-15", "open": 10.96, "high": 11.03, "low": 10.58, "close": 10.68, "volume": 2905961, "pctChg": -2.02, "turn": 2.43}, {"date": "2026-06-16", "open": 10.73, "high": 10.94, "low": 10.37, "close": 10.94, "volume": 2521407, "pctChg": 2.43, "turn": 2.1}, {"date": "2026-06-17", "open": 10.92, "high": 11.01, "low": 10.6, "close": 10.62, "volume": 2206563, "pctChg": -2.92, "turn": 1.84}, {"date": "2026-06-18", "open": 10.75, "high": 10.75, "low": 10.43, "close": 10.58, "volume": 2325528, "pctChg": -0.38, "turn": 1.94}, {"date": "2026-06-22", "open": 10.48, "high": 10.59, "low": 10.08, "close": 10.5, "volume": 2659998, "pctChg": -0.76, "turn": 2.22}, {"date": "2026-06-24", "open": 10.5, "high": 10.72, "low": 9.96, "close": 10.14, "volume": 2946708, "pctChg": -2.59, "turn": 2.46}, {"date": "2026-06-26", "open": 9.96, "high": 10.32, "low": 9.86, "close": 9.98, "volume": 3052613, "pctChg": -0.8, "turn": 2.55}, {"date": "2026-06-29", "open": 9.99, "high": 10.17, "low": 9.56, "close": 10.02, "volume": 3396720, "pctChg": 0.4, "turn": 0.85}, {"date": "2026-06-30", "open": 10.02, "high": 10.33, "low": 9.91, "close": 10.19, "volume": 2772734, "pctChg": 1.7, "turn": 0.69}, {"date": "2026-07-01", "open": 10.27, "high": 10.55, "low": 9.93, "close": 10.3, "volume": 3516588, "pctChg": 1.08, "turn": 0.88}, {"date": "2026-07-02", "open": 10.18, "high": 10.57, "low": 10.01, "close": 10.01, "volume": 3282402, "pctChg": -2.82, "turn": 0.82}]}