{"code": "sh.688523", "name": "航天环宇", "concept": "大飞机", "history": [{"date": "2026-05-29", "rank": 1889, "total": 1.1, "washout_quality": 0.0, "probe_test": 15.0, "ma_convergence": 5.3, "stock_strength": 16.1, "launch_readiness": 6.7, "volume_price_health": 35.1, "trend_class": "choppy", "trend_class_score": 50.0, "swing_confidence": 1.0}, {"date": "2026-06-01", "rank": 1927, "total": 2.4, "washout_quality": 51.6, "probe_test": 15.0, "ma_convergence": 0.0, "stock_strength": 21.4, "launch_readiness": 10.4, "volume_price_health": 33.7, "trend_class": "choppy", "trend_class_score": 50.0, "swing_confidence": 1.0}, {"date": "2026-06-02", "rank": 1951, "total": 1.1, "washout_quality": 0.0, "probe_test": 15.0, "ma_convergence": 0.0, "stock_strength": 17.9, "launch_readiness": 15.1, "volume_price_health": 38.5, "trend_class": "choppy", "trend_class_score": 50.0, "swing_confidence": 1.0}, {"date": "2026-06-03", "rank": 1787, "total": 3.7, "washout_quality": 52.1, "probe_test": 15.0, "ma_convergence": 0.0, "stock_strength": 30.3, "launch_readiness": 30.8, "volume_price_health": 36.9, "trend_class": "choppy", "trend_class_score": 50.0, "swing_confidence": 1.0}, {"date": "2026-06-04", "rank": 1736, "total": 2.9, "washout_quality": 51.9, "probe_test": 15.0, "ma_convergence": 0.0, "stock_strength": 23.4, "launch_readiness": 31.2, "volume_price_health": 37.7, "trend_class": "choppy", "trend_class_score": 50.0, "swing_confidence": 1.0}, {"date": "2026-06-05", "rank": 1704, "total": 6.9, "washout_quality": 51.9, "probe_test": 15.0, "ma_convergence": 10.0, "stock_strength": 38.0, "launch_readiness": 100.0, "volume_price_health": 45.5, "trend_class": "choppy", "trend_class_score": 50.0, "swing_confidence": 1.0}, {"date": "2026-06-08", "rank": 1526, "total": 7.5, "washout_quality": 51.7, "probe_test": 15.0, "ma_convergence": 22.3, "stock_strength": 29.4, "launch_readiness": 97.2, "volume_price_health": 32.6, "trend_class": "choppy", "trend_class_score": 50.0, "swing_confidence": 1.0}, {"date": "2026-06-09", "rank": 1468, "total": 12.3, "washout_quality": 51.7, "probe_test": 15.0, "ma_convergence": 32.5, "stock_strength": 33.5, "launch_readiness": 100.0, "volume_price_health": 32.0, "trend_class": "choppy", "trend_class_score": 50.0, "swing_confidence": 1.0}, {"date": "2026-06-10", "rank": 1591, "total": 3.4, "washout_quality": 0.0, "probe_test": 15.0, "ma_convergence": 22.0, "stock_strength": 9.4, "launch_readiness": 76.9, "volume_price_health": 26.8, "trend_class": "choppy", "trend_class_score": 50.0, "swing_confidence": 1.0}, {"date": "2026-06-11", "rank": 1536, "total": 3.8, "washout_quality": 0.0, "probe_test": 15.0, "ma_convergence": 23.1, "stock_strength": 9.4, "launch_readiness": 71.8, "volume_price_health": 41.9, "trend_class": "choppy", "trend_class_score": 50.0, "swing_confidence": 1.0}, {"date": "2026-06-12", "rank": 1215, "total": 10.8, "washout_quality": 0.0, "probe_test": 50.4, "ma_convergence": 23.9, "stock_strength": 9.4, "launch_readiness": 9.0, "volume_price_health": 37.9, "trend_class": "choppy", "trend_class_score": 50.0, "swing_confidence": 1.0}, {"date": "2026-06-15", "rank": 1465, "total": 11.7, "washout_quality": 0.0, "probe_test": 50.4, "ma_convergence": 27.5, "stock_strength": 9.4, "launch_readiness": 2.4, "volume_price_health": 42.6, "trend_class": "choppy", "trend_class_score": 50.0, "swing_confidence": 1.0}, {"date": "2026-06-16", "rank": 1503, "total": 8.6, "washout_quality": 0.0, "probe_test": 50.4, "ma_convergence": 14.4, "stock_strength": 9.4, "launch_readiness": 1.8, "volume_price_health": 44.2, "trend_class": "choppy", "trend_class_score": 50.0, "swing_confidence": 1.0}, {"date": "2026-06-17", "rank": 1286, "total": 11.1, "washout_quality": 0.0, "probe_test": 50.4, "ma_convergence": 24.8, "stock_strength": 9.4, "launch_readiness": 5.0, "volume_price_health": 43.6, "trend_class": "choppy", "trend_class_score": 50.0, "swing_confidence": 1.0}, {"date": "2026-06-18", "rank": 1071, "total": 17.7, "washout_quality": 0.0, "probe_test": 50.4, "ma_convergence": 37.9, "stock_strength": 9.4, "launch_readiness": 17.8, "volume_price_health": 48.0, "trend_class": "choppy", "trend_class_score": 50.0, "swing_confidence": 1.0}, {"date": "2026-06-22", "rank": 972, "total": 18.6, "washout_quality": 0.0, "probe_test": 50.4, "ma_convergence": 39.0, "stock_strength": 9.4, "launch_readiness": 14.1, "volume_price_health": 55.4, "trend_class": "choppy", "trend_class_score": 50.0, "swing_confidence": 1.0}, {"date": "2026-06-24", "rank": 261, "total": 16.7, "washout_quality": 0.0, "probe_test": 50.4, "ma_convergence": 36.2, "stock_strength": 9.4, "launch_readiness": 9.1, "volume_price_health": 55.6, "trend_class": "choppy", "trend_class_score": 50.0, "swing_confidence": 1.0}, {"date": "2026-06-26", "rank": 557, "total": 25.4, "washout_quality": 0.0, "probe_test": 77.4, "ma_convergence": 41.6, "stock_strength": 9.4, "launch_readiness": 11.1, "volume_price_health": 57.7, "trend_class": "choppy", "trend_class_score": 50.0, "swing_confidence": 1.0}, {"date": "2026-06-29", "rank": 611, "total": 22.1, "washout_quality": 0.0, "probe_test": 77.4, "ma_convergence": 37.6, "stock_strength": 9.4, "launch_readiness": 12.0, "volume_price_health": 47.9, "trend_class": "choppy", "trend_class_score": 50.0, "swing_confidence": 1.0}, {"date": "2026-06-30", "rank": 502, "total": 35.6, "washout_quality": 0.0, "probe_test": 77.4, "ma_convergence": 47.6, "stock_strength": 9.4, "launch_readiness": 86.9, "volume_price_health": 46.2, "trend_class": "choppy", "trend_class_score": 50.0, "swing_confidence": 1.0}, {"date": "2026-07-01", "rank": 534, "total": 36.4, "washout_quality": 0.0, "probe_test": 77.4, "ma_convergence": 49.6, "stock_strength": 9.4, "launch_readiness": 86.1, "volume_price_health": 41.7, "trend_class": "choppy", "trend_class_score": 50.0, "swing_confidence": 1.0}, {"date": "2026-07-02", "rank": 598, "total": 31.3, "washout_quality": 0.0, "probe_test": 77.4, "ma_convergence": 44.6, "stock_strength": 9.4, "launch_readiness": 67.5, "volume_price_health": 43.8, "trend_class": "choppy", "trend_class_score": 50.0, "swing_confidence": 1.0}, {"date": "2026-07-03", "rank": 555, "total": 46.9, "washout_quality": 51.2, "probe_test": 77.4, "ma_convergence": 50.0, "stock_strength": 30.5, "launch_readiness": 55.4, "volume_price_health": 58.5, "trend_class": "choppy", "trend_class_score": 50.0, "swing_confidence": 1.0}, {"date": "2026-07-06", "rank": 1699, "total": 0.0, "washout_quality": 0.0, "probe_test": 0.0, "ma_convergence": 0.0, "stock_strength": 0.0, "launch_readiness": 0.0, "volume_price_health": 0.0, "trend_class": "choppy", "trend_class_score": 0.0, "swing_confidence": 0.0}, {"date": "2026-07-07", "rank": 1579, "total": 0.0, "washout_quality": 0.0, "probe_test": 0.0, "ma_convergence": 0.0, "stock_strength": 0.0, "launch_readiness": 0.0, "volume_price_health": 0.0, "trend_class": "choppy", "trend_class_score": 0.0, "swing_confidence": 0.0}], "kline": [{"date": "2026-05-22", "open": 66.67, "high": 68.65, "low": 65.08, "close": 68.02, "volume": 5773145, "pctChg": 2.02, "turn": 5.98}, {"date": "2026-05-25", "open": 68.5, "high": 69.79, "low": 66.59, "close": 68.02, "volume": 5954873, "pctChg": 0.0, "turn": 6.17}, {"date": "2026-05-26", "open": 67.61, "high": 68.06, "low": 63.0, "close": 64.2, "volume": 6835382, "pctChg": -5.62, "turn": 7.08}, {"date": "2026-05-27", "open": 65.0, "high": 65.1, "low": 61.08, "close": 61.79, "volume": 5330641, "pctChg": -3.75, "turn": 5.52}, {"date": "2026-05-28", "open": 62.1, "high": 64.27, "low": 61.08, "close": 62.77, "volume": 5285626, "pctChg": 1.59, "turn": 5.48}, {"date": "2026-05-29", "open": 62.77, "high": 62.82, "low": 56.0, "close": 56.43, "volume": 8288065, "pctChg": -10.1, "turn": 8.59}, {"date": "2026-06-01", "open": 57.55, "high": 59.85, "low": 56.43, "close": 57.28, "volume": 7784445, "pctChg": 1.51, "turn": 8.07}, {"date": "2026-06-02", "open": 57.85, "high": 57.86, "low": 54.8, "close": 56.72, "volume": 4742176, "pctChg": -0.98, "turn": 1.17}, {"date": "2026-06-03", "open": 57.0, "high": 61.09, "low": 56.39, "close": 58.75, "volume": 6506382, "pctChg": 3.58, "turn": 1.6}, {"date": "2026-06-04", "open": 57.3, "high": 58.49, "low": 56.62, "close": 57.6, "volume": 4046146, "pctChg": -1.96, "turn": 0.99}, {"date": "2026-06-05", "open": 58.24, "high": 60.98, "low": 57.37, "close": 60.09, "volume": 9982845, "pctChg": 4.32, "turn": 2.45}, {"date": "2026-06-08", "open": 57.8, "high": 62.39, "low": 56.8, "close": 58.6, "volume": 7720784, "pctChg": -2.48, "turn": 1.9}, {"date": "2026-06-09", "open": 57.43, "high": 61.5, "low": 57.43, "close": 59.29, "volume": 8023105, "pctChg": 1.18, "turn": 1.97}, {"date": "2026-06-10", "open": 58.7, "high": 59.9, "low": 52.57, "close": 52.99, "volume": 10829786, "pctChg": -10.63, "turn": 2.66}, {"date": "2026-06-11", "open": 53.05, "high": 54.1, "low": 50.7, "close": 53.27, "volume": 10087735, "pctChg": 0.53, "turn": 2.48}, {"date": "2026-06-12", "open": 53.56, "high": 57.52, "low": 52.46, "close": 53.35, "volume": 12717836, "pctChg": 0.15, "turn": 3.13}, {"date": "2026-06-15", "open": 53.99, "high": 55.0, "low": 52.85, "close": 53.84, "volume": 6715890, "pctChg": 0.92, "turn": 1.65}, {"date": "2026-06-16", "open": 55.0, "high": 55.59, "low": 51.88, "close": 52.63, "volume": 7927169, "pctChg": -2.25, "turn": 1.95}, {"date": "2026-06-17", "open": 52.63, "high": 54.61, "low": 51.67, "close": 53.2, "volume": 6155116, "pctChg": 1.08, "turn": 1.51}, {"date": "2026-06-18", "open": 52.51, "high": 55.21, "low": 51.89, "close": 54.18, "volume": 6023223, "pctChg": 1.84, "turn": 1.48}, {"date": "2026-06-22", "open": 54.0, "high": 54.18, "low": 51.2, "close": 52.84, "volume": 5619414, "pctChg": -2.47, "turn": 1.38}, {"date": "2026-06-24", "open": 50.3, "high": 51.98, "low": 48.5, "close": 50.95, "volume": 5151482, "pctChg": 1.13, "turn": 1.27}, {"date": "2026-06-26", "open": 48.8, "high": 53.2, "low": 47.27, "close": 51.5, "volume": 10239732, "pctChg": 3.19, "turn": 2.52}, {"date": "2026-06-29", "open": 51.43, "high": 51.5, "low": 49.0, "close": 49.95, "volume": 7046122, "pctChg": -3.01, "turn": 1.73}, {"date": "2026-06-30", "open": 50.26, "high": 54.04, "low": 49.85, "close": 52.4, "volume": 7107846, "pctChg": 4.9, "turn": 1.75}, {"date": "2026-07-01", "open": 52.91, "high": 54.28, "low": 52.1, "close": 53.13, "volume": 6427567, "pctChg": 1.39, "turn": 1.58}, {"date": "2026-07-02", "open": 52.92, "high": 53.8, "low": 50.4, "close": 50.58, "volume": 6106350, "pctChg": -4.8, "turn": 1.5}, {"date": "2026-07-03", "open": 51.48, "high": 59.99, "low": 51.25, "close": 58.79, "volume": 13191202, "pctChg": 16.23, "turn": 3.24}, {"date": "2026-07-06", "open": 59.69, "high": 59.73, "low": 52.63, "close": 53.57, "volume": 12149448, "pctChg": -8.88, "turn": 2.99}, {"date": "2026-07-07", "open": 53.08, "high": 54.8, "low": 49.95, "close": 50.24, "volume": 7725726, "pctChg": -6.22, "turn": 1.9}]}